{"traits": {"TnyUVrVIwg5-Q7v1T": {"name": "One of:", "children": {"tzVksrwP6XfkfU3H_": {"name": "Talent (Healer)", "tags": ["Advantage", "Mental", "Talent"], "modifiers": {"mbxsG5DRNKBOLPtQp": {"name": "Alternate Benefit"}, "mp_yVsgjV1WFeFm_5": {"name": "Alternative Cost"}}, "features": [{"name": {"qualifier": "Diagnosis"}}, {"name": {"qualifier": "Esoteric Medicine"}}, {"name": {"qualifier": "First Aid"}}, {"name": {"qualifier": "Pharmacy"}}, {"name": {"qualifier": "Physician"}}, {"name": {"qualifier": "Physiology"}}, {"name": {"qualifier": "Psychology"}}, {"name": {"qualifier": "Surgery"}}, {"name": {"qualifier": "Veterinary"}}, {}, {}, {}, {"situation": "from patients"}], "prereqs": {"prereqs": [{"name": {"qualifier": "Talent (Healer)"}, "notes": {"qualifier": "Modern"}}]}}}}, "tr6k3eskG7Cc53NRo": {"name": "High Manual Dexterity", "tags": ["Advantage", "Physical"], "features": [{"name": {"qualifier": "artist"}}, {"name": {"qualifier": "jeweler"}}, {"name": {"qualifier": "knot-tying"}}, {"name": {"qualifier": "leatherworking"}}, {"name": {"qualifier": "lockpicking"}}, {"name": {"qualifier": "pickpocket"}}, {"name": {"qualifier": "sewing"}}, {"name": {"qualifier": "sleight of hand"}}, {"name": {"qualifier": "surgery"}}, {"name": {"qualifier": "machinist"}}, {"name": {"qualifier": "mechanic"}}]}}, "skills": {"S5wE-3EDFLLlnC9jV": {"name": "Type", "children": {"Sk0g4L4nX0Nw-4PFa": {"name": "Doctor", "children": {"sjfYU3ruLlvlBcWe0": {"name": "Diagnosis", "tags": ["Medical"], "defaults": [{}, {"name": "First Aid"}, {"name": "Physician"}, {"name": "Veterinary"}]}, "s3fS8ST154nJMVlxI": {"name": "Esoteric Medicine", "tags": ["Esoteric", "Medical"], "defaults": [{}]}, "satY_F1RnL81ZaGrQ": {"name": "Naturalist", "tags": ["Animal", "Exploration", "Natural Science", "Outdoor", "Plant"], "specialization": "Earthlike", "defaults": [{}, {"name": "Biology"}]}, "sGlAQGsT0421Y9_l_": {"name": "Pharmacy", "tags": ["Design", "Invention", "Medical", "Plant"], "specialization": "Herbal", "prereqs": {"prereqs": [{"name": {"qualifier": "naturalist"}}]}, "defaults": [{}, {"name": "Biology"}, {"name": "Herb Lore"}, {"name": "Naturalist"}]}, "SBwyibt36UFOf9D6b": {"name": "Two of:", "children": {"sRVJspij4SvSc_mD5": {"name": "Alchemy", "tags": ["Magical", "Natural Science", "Occult"]}, "sAj5KpPoRbIL_Achs": {"name": "Chemistry", "tags": ["Natural Science"], "defaults": [{}, {"name": "Alchemy"}]}, "syveehsz3oqrj9TVn": {"name": "Esoteric Medicine", "tags": ["Esoteric", "Medical"], "defaults": [{}]}, "sg49qQAeZCOR-guFM": {"name": "Expert Skill", "tags": ["Humanities", "Knowledge", "Scholarly", "Social Sciences"], "specialization": "Thanatology"}, "sex4OJJjyBotjIgUJ": {"name": "Naturalist", "tags": ["Animal", "Exploration", "Natural Science", "Outdoor", "Plant"], "specialization": "Earthlike", "defaults": [{}, {"name": "Biology"}]}, "s9B6RCehc1bsTxTF7": {"name": "Pharmacy", "tags": ["Design", "Invention", "Medical", "Plant"], "specialization": "Herbal", "prereqs": {"prereqs": [{"name": {"qualifier": "naturalist"}}]}, "defaults": [{}, {"name": "Biology"}, {"name": "Herb Lore"}, {"name": "Naturalist"}]}, "sCEIKHHacotT1es76": {"name": "Physiology", "tags": ["Medical", "Natural Science"], "specialization": "@Specialty@", "defaults": [{}, {"name": "Diagnosis"}, {"name": "Physician"}, {"name": "Surgery"}]}, "sYLEwievHzsH7KRg-": {"name": "Poisons", "tags": ["Criminal", "Medical", "Spy", "Street"], "defaults": [{}, {"name": "Chemistry"}, {"name": "Pharmacy"}, {"name": "Physician"}]}, "sqJhUzyCGxqC7_TZ7": {"name": "Professional Skill", "tags": ["Knowledge"], "specialization": "Massage", "defaults": [{}]}, "sSgb24bfcTFH6Btkf": {"name": "Psychology", "tags": ["Humanities", "Social Sciences"], "defaults": [{}, {"name": "Sociology"}]}, "sFVZS0bUfDcJctbqv": {"name": "Surgery", "tags": ["Medical"], "prereqs": {"prereqs": [{"name": {"qualifier": "first aid"}}, {"name": {"qualifier": "physician"}}]}, "defaults": [{"name": "First Aid"}, {"name": "Physician"}, {"name": "Physiology"}, {"name": "Veterinary"}]}}}}}, "SB1XkTMWYW32-pStQ": {"name": "Surgeon", "children": {"svvKvHLUNeO8uaZ83": {"name": "Diagnosis", "tags": ["Medical"], "defaults": [{}, {"name": "First Aid"}, {"name": "Physician"}, {"name": "Veterinary"}]}, "s-KfOSUiwDTkaUsWw": {"name": "First Aid", "tags": ["Everyman", "Medical"], "defaults": [{}, {"name": "Esoteric Medicine"}, {"name": "Physician"}, {"name": "Veterinary"}]}, "s7slY4lyC_xMfJNdl": {"name": "Surgery", "tags": ["Medical"], "prereqs": {"prereqs": [{"name": {"qualifier": "first aid"}}, {"name": {"qualifier": "physician"}}]}, "defaults": [{"name": "First Aid"}, {"name": "Physician"}, {"name": "Physiology"}, {"name": "Veterinary"}]}, "SVxL8CZkr_uY_dKTp": {"name": "Three of:", "children": {"s0a8zdASGYeyW287N": {"name": "Alchemy", "tags": ["Magical", "Natural Science", "Occult"]}, "sD-CERjAlgODe8nan": {"name": "Chemistry", "tags": ["Natural Science"], "defaults": [{}, {"name": "Alchemy"}]}, "sRU86Vrn-vMrPkdNt": {"name": "Esoteric Medicine", "tags": ["Esoteric", "Medical"], "defaults": [{}]}, "sPpWtxaxf6s5y9cS2": {"name": "Expert Skill", "tags": ["Humanities", "Knowledge", "Scholarly", "Social Sciences"], "specialization": "Thanatology"}, "sVUqTbhw0SrUY5aVf": {"name": "Naturalist", "tags": ["Animal", "Exploration", "Natural Science", "Outdoor", "Plant"], "specialization": "Earthlike", "defaults": [{}, {"name": "Biology"}]}, "sLZy1yRRlQ3445vUZ": {"name": "Pharmacy", "tags": ["Design", "Invention", "Medical", "Plant"], "specialization": "Herbal", "prereqs": {"prereqs": [{"name": {"qualifier": "naturalist"}}]}, "defaults": [{}, {"name": "Biology"}, {"name": "Herb Lore"}, {"name": "Naturalist"}]}, "sxUiV59QbIGZOcsEu": {"name": "Physiology", "tags": ["Medical", "Natural Science"], "specialization": "@Specialty@", "defaults": [{}, {"name": "Diagnosis"}, {"name": "Physician"}, {"name": "Surgery"}]}, "szw2fSNc_qy71U0MX": {"name": "Poisons", "tags": ["Criminal", "Medical", "Spy", "Street"], "defaults": [{}, {"name": "Chemistry"}, {"name": "Pharmacy"}, {"name": "Physician"}]}, "sgKaLgd9eillMib6o": {"name": "Professional Skill", "tags": ["Knowledge"], "specialization": "Massage", "defaults": [{}]}, "sX40mqXUezS1h966_": {"name": "Psychology", "tags": ["Humanities", "Social Sciences"], "defaults": [{}, {"name": "Sociology"}]}}}}}}}}, "notes": {"nzx9NewASYl5sdTr-": {}}}