{"traits": {"T_--IYDk1kFTrD9nK": {"name": "Healing Cleric", "children": {"TnVH7rDx6gzbfL92e": {"name": "Attributes", "children": {"tDkyf-81dG7rSwKgQ": {"name": "Increased Dexterity", "tags": ["Advantage", "Attribute", "Physical"], "modifiers": {"mw1fALhIKIV7kvW6R": {"name": "No Fine Manipulators"}}, "features": [{}]}, "tBsdGC2Qs-80D4qSR": {"name": "Increased Health", "tags": ["Advantage", "Attribute", "Physical"], "features": [{}]}, "toHURDGzvLxzrZddj": {"name": "Increased Intelligence", "tags": ["Advantage", "Attribute", "Mental"], "features": [{}]}, "t6FESmsrM8EzRd4mQ": {"name": "Increased Strength", "tags": ["Advantage", "Attribute", "Physical"], "modifiers": {"mNUqHozTW0xo9T3Wl": {"name": "No Fine Manipulators"}, "mzjAgkpwD254OVtAd": {"name": "Size"}, "mS3pp-hwrSXXHGVdD": {"name": "Super-Effort"}}, "features": [{}]}}}, "T1UI6yV6AhQL7Bd3L": {"name": "Class Advantages", "children": {"T7MJtIkzbWaFITG0f": {"name": "20 Points Chosen From:", "notes": "or from additional holy Abilities", "children": {"tRHN6WUuqgm9OgYzS": {"name": "Extra Fatigue Points", "tags": ["Advantage", "Attribute", "Physical"], "features": [{}]}, "t1fgInQ2byJ11xJId": {"name": "Fearlessness", "tags": ["Advantage", "Mental"]}, "tP2WdDBnftiq5I-0U": {"name": "Increased Dexterity", "tags": ["Advantage", "Attribute", "Physical"], "modifiers": {"mASyx0VislidEC9gS": {"name": "No Fine Manipulators"}}, "features": [{}]}, "tSOPvAn6R5YGhOkIJ": {"name": "Increased Health", "tags": ["Advantage", "Attribute", "Physical"], "features": [{}]}, "trCGC_cN5_N0QKpqY": {"name": "Increased Intelligence", "tags": ["Advantage", "Attribute", "Mental"], "features": [{}]}, "tR5IXyqNYOTO0iIG4": {"name": "Increased Strength", "tags": ["Advantage", "Attribute", "Physical"], "modifiers": {"mcvfhmSXBLDoYMgHw": {"name": "No Fine Manipulators"}, "m10qK9X08nJpx6oyc": {"name": "Size"}, "miipJcMA0M1N-rNh1": {"name": "Super-Effort"}}, "features": [{}]}, "tDToJwq8RD0t0gLGy": {"name": "Increased Will", "tags": ["Advantage", "Attribute", "Mental"], "features": [{}]}, "tdym8sPapRyWKPdZ4": {"name": "Language: @Language@", "tags": ["Advantage", "Language", "Mental"], "modifiers": {"mXLmqfHQPTbcc7Krc": {"name": "Native"}, "mn3SS4GykjchSJyyj": {"name": "Spoken", "notes": "None"}, "mVMD6bDnB6MtilCaU": {"name": "Spoken", "notes": "Broken"}, "mBRAljfrjnXvsjLar": {"name": "Spoken", "notes": "Accented"}, "mVnsP4YTwCtAVcShv": {"name": "Spoken", "notes": "Native"}, "mtZtt5VqNRac4FDZj": {"name": "Written", "notes": "None"}, "mV_kW3OON8iUQpK3a": {"name": "Written", "notes": "Broken"}, "mDH1nm12jblCMnd3w": {"name": "Written", "notes": "Accented"}, "mbWKhHZfEZm9yYJut": {"name": "Written", "notes": "Native"}}, "prereqs": {"prereqs": [{"name": {"qualifier": "Language Talent"}}]}}, "t8XwDaEspW2VxcJmn": {"name": "Luck", "tags": ["Advantage", "Mental"], "notes": "Usable once per hour of play", "modifiers": {"maIs-P9ysVKXxklQa": {"name": "Active"}, "m5nhe16pnevgf3k-u": {"name": "Aspected", "notes": "@Aspect@"}, "m2wfW-Id6CQSD1nop": {"name": "Defensive"}, "mfhbB7ujuzBcymlN2": {"name": "Wishing"}}}, "tNlgS5kAaW4xysZdi": {"name": "Mind Shield", "tags": ["Advantage", "Exotic", "Mental"], "modifiers": {"mYaVxIB8W9WEKsXlv": {"name": "Cybernetic"}, "mcwbnqKp3dF3KwVUd": {"name": "Limited", "notes": "@Source@"}, "mPhVlnO1pC7YdjgAD": {"name": "Limited", "notes": "@Power/College/Focus@"}}}, "t-yHLvjjjr6WLgPMY": {"name": "Power Investiture", "tags": ["Advantage", "Mental", "Supernatural"], "features": [{"name": {"qualifier": "Clerical"}}]}, "tSyStLH243qrzsxe1": {"name": "Resistant", "tags": ["Advantage", "Physical"], "modifiers": {"mvC3RDLhIW5jv3RGD": {"name": "@Very Common: Metabolic Hazards, etc.@"}, "mpt3Uuze5mv4W_eNI": {"name": "@Common: Poison, Sickness, etc.@"}, "mV8qXo1xJH1Etp7Ib": {"name": "Disease"}, "m8tnaGnjLVd7ezaTb": {"name": "@Rare: Acceleration, Altitude Sickness, Bends, Seasickness, Space Sickness, Nanomachines, etc.@"}, "m54VCkEHGcOEnqtiM": {"name": "Immunity"}, "mwnUEO6bM7fxa3Mjh": {"name": "+8 to all HT rolls to resist"}, "mPDXEWl9jNKwfG6Fc": {"name": "+3 to all HT rolls to resist"}}}, "tWa9bZsTPFKu8hay5": {"name": "Resistant", "tags": ["Advantage", "Physical"], "modifiers": {"me0w61SC_glHLYZP3": {"name": "@Very Common: Metabolic Hazards, etc.@"}, "mwsBDSf1G338xGwKH": {"name": "@Common: Poison, Sickness, etc.@"}, "m2qupO8bbYZbfFD6i": {"name": "Disease"}, "mdmcUrMZU5-q6ffNl": {"name": "@Rare: Acceleration, Altitude Sickness, Bends, Seasickness, Space Sickness, Nanomachines, etc.@"}, "m_Ue8Pr194VBlAC-Y": {"name": "Immunity"}, "muFNa1o2mHazVcJxF": {"name": "+8 to all HT rolls to resist"}, "mXHmJeenT3JMAepdh": {"name": "+3 to all HT rolls to resist"}}}, "tSNTvwWBjkYU08KY2": {"name": "Signature Gear", "tags": ["Advantage", "Social"]}, "t64qW6-YU5nmFLY2J": {"name": "Talent (Healer)", "tags": ["Advantage", "Mental"], "features": [{"name": {"qualifier": "diagnosis"}}, {"name": {"qualifier": "esoteric medicine"}}, {"name": {"qualifier": "first aid"}}, {"name": {"qualifier": "pharmacy"}}, {"name": {"qualifier": "physician"}}, {"name": {"qualifier": "physiology"}}, {"name": {"qualifier": "psychology"}}, {"name": {"qualifier": "surgery"}}, {"name": {"qualifier": "veterinary"}}]}, "toctndDOrVMB2UpWs": {"name": "Unfazeable", "tags": ["Advantage", "Mental"]}}}, "T79a0e_92kJzPDFW8": {"name": "25 Points in holy abilities", "notes": "put leftovers into spells", "children": {"T_6Y6sIGq0csX1NNI": {"name": "Holy Might", "tags": ["Advantage"], "children": {"tKxIn8nGjklhkb5dS": {"name": "Ally (@Divine servant of equal points@)", "tags": ["Advantage", "Social"], "modifiers": {"mW-eHT0Lv0pk-rWTX": {"name": "Point total", "notes": "25% of your starting points"}, "mKDM9URllYABBXr6q": {"name": "Point total", "notes": "50% of your starting points"}, "mFsg_6JpwMnn8V42v": {"name": "Point total", "notes": "75% of your starting points"}, "mcipIpyU6NCIRxxnK": {"name": "Point total", "notes": "100% of your starting points"}, "muNtQq9P9hFYtFX3r": {"name": "Point total", "notes": "150% of your starting points"}, "mNovFBmh4BHoWYLlz": {"name": "Appears constantly", "notes": "No roll required"}, "mSxdjAVoqPa93K1es": {"name": "Appears almost all the time", "notes": "15-"}, "myKybgGdReuMU99Q8": {"name": "Appears quite often", "notes": "12-"}, "mj3OpWFwpprYT9KT1": {"name": "Appears fairly often", "notes": "9-"}, "mcNjzSBAaWVG_kAuM": {"name": "Appears quite rarely", "notes": "6-"}, "mKKlv3QS0CMLLuwbU": {"name": "Group of 6-10"}, "mhhp3OO8Jl3k_4eWb": {"name": "Group of 11-20"}, "m8CewDmBM0ArrACe7": {"name": "Group of 21-50"}, "mEu1npzcB59GRNlMp": {"name": "Group of 51-100"}, "mYs7SPEwUWgqQkdb6": {"name": "Group of 101-1000"}, "mPWaHRnRcRyvFMgCK": {"name": "Group of 1001-10000"}, "mMjtG4Kh1Rl09AuIK": {"name": "Group of 10001-100000"}, "mI6GBXlcpknOIjaY_": {"name": "Group of 100001-1000000"}, "mFFkzgxQSqorc_buC": {"name": "Minion"}, "mJ4OVa5Qzs0wqbDHA": {"name": "Minion", "notes": "IQ 0 or Slave Mentality"}, "m5hGhYLB3SmQWa33n": {"name": "Special Abilities", "notes": "@Abilities@"}, "m9u7EMCE83DI9qlKU": {"name": "Summonable"}, "mA_4AN8T8gAo2120l": {"name": "Sympathy", "notes": "Death of one party reduces the other to 0 HP"}, "m2xSKjQkjQ8eGMlCe": {"name": "Sympathy", "notes": "Death of one party reduces the other to 0 HP and wounds affect ally but not you"}, "m9Bai-NsJizxK6NY_": {"name": "Sympathy", "notes": "Death of one party kills the other"}, "mnGgltbgNrMxDVjeq": {"name": "Sympathy", "notes": "Death of one party kills the other and wounds affect ally but not you"}, "mBtzE-6JenEK1EyxG": {"name": "Unwilling"}, "miCikasy91k1-dMjy": {"name": "Favor"}}}, "tu4JxNT9E2GFIlCKU": {"name": "Ally (@Divine servant of equal points@)", "tags": ["Advantage", "Social"], "modifiers": {"mNAGY4WkTpQCVkqON": {"name": "Point total", "notes": "25% of your starting points"}, "mmqKSJSwKQuhZ-SQB": {"name": "Point total", "notes": "50% of your starting points"}, "mwn0s8xO5JN3meZOi": {"name": "Point total", "notes": "75% of your starting points"}, "mRnjJxi6DUSIY66WJ": {"name": "Point total", "notes": "100% of your starting points"}, "mVBj_BPxv2djiEV17": {"name": "Point total", "notes": "150% of your starting points"}, "mfHNq_mxUtx6AlAh8": {"name": "Appears constantly", "notes": "No roll required"}, "mJpGh-7x6PCMNhhho": {"name": "Appears almost all the time", "notes": "15-"}, "mmYh2f_qGEuVctOF7": {"name": "Appears quite often", "notes": "12-"}, "mc0hqkDkPEHGZOjbC": {"name": "Appears fairly often", "notes": "9-"}, "m5OSnw1t9Mp8Sd62h": {"name": "Appears quite rarely", "notes": "6-"}, "mRhZeAL_lo1Uf7lu1": {"name": "Group of 6-10"}, "mXIyzvTVy0enLiyEC": {"name": "Group of 11-20"}, "mS7qMWZFf9GU6E8cp": {"name": "Group of 21-50"}, "mtLL_6WWg0hdulIlC": {"name": "Group of 51-100"}, "mnJosFdJl0TfDYbMw": {"name": "Group of 101-1000"}, "mnqc2PeAecOapmoB6": {"name": "Group of 1001-10000"}, "mOxk2hAPEwgdgh0PO": {"name": "Group of 10001-100000"}, "mvsL9zFIxF8Gyc866": {"name": "Group of 100001-1000000"}, "mX8qvzJfCRGGksbR9": {"name": "Minion"}, "mqtUKBn_6uUu6zY6K": {"name": "Minion", "notes": "IQ 0 or Slave Mentality"}, "msP0H8AjkeE3lDGI4": {"name": "Special Abilities", "notes": "@Abilities@"}, "mXjCi5LFSnYHTx1AY": {"name": "Summonable"}, "mi-z8I2_LypH9L-gX": {"name": "Sympathy", "notes": "Death of one party reduces the other to 0 HP"}, "mMF6upKOK5B9FKyE7": {"name": "Sympathy", "notes": "Death of one party reduces the other to 0 HP and wounds affect ally but not you"}, "mw-wRsl-BJOV71Ajr": {"name": "Sympathy", "notes": "Death of one party kills the other"}, "m3EQyKNXzkO9GeGVD": {"name": "Sympathy", "notes": "Death of one party kills the other and wounds affect ally but not you"}, "mU7pb6UmfCDAtHuFr": {"name": "Unwilling"}, "mRlOWUK_EQMLveUDo": {"name": "Favor"}}}, "tm51egdZSqct2Qe09": {"name": "Blessed", "tags": ["Advantage", "Mental", "Supernatural"]}, "tArHAtU8SQfgDU0_4": {"name": "Detect", "tags": ["Advantage", "Exotic", "Mental", "Physical"], "modifiers": {"m7aO_nKSMf-b_C4uQ": {"name": "@Rare Substance/Condition@"}, "md_xGqaOZkBV8dST_": {"name": "@Occasional Substance/Condition@"}, "mNWn0vraszjqsm1pi": {"name": "@evil, good or  supernatural beings@"}, "mQUPDzvV9XFhODMmf": {"name": "@Very Common Substance/Condition@"}, "mSA49Ca6EEWicdWVL": {"name": "Precise"}, "mFsFeiv3uvH2N60SU": {"name": "Signal Detection"}, "m14KBdzPnzdlPta8T": {"name": "Vague"}, "m1stJwzWnwu2L5l87": {"name": "Analyzing"}}}, "tJhbjsCLXlDcFx1Fm": {"name": "Healing", "tags": ["Advantage", "Exotic", "Mental"], "modifiers": {"mrLFWohmvozxglVBb": {"name": "Faith Healing"}, "mv8U-RHE0o5bT0vN7": {"name": "Xenohealing", "notes": "All Mammals"}, "mPMNqwkDk7GvcL-6_": {"name": "Xenohealing", "notes": "All Earthly Life"}, "m4PXlfNzhI4O1BvIK": {"name": "Xenohealing", "notes": "All Carbon-Based Life"}, "mTF5DTzhP71OqVfvf": {"name": "Xenohealing", "notes": "Anything Alive"}, "mRDR-ztLJGvgd6eWw": {"name": "Xenohealing", "notes": "Anything Animate"}, "m39gkNlasaBIPFp1I": {"name": "Disease Only"}, "m6a7_LIOU6TcpGWhp": {"name": "Injuries Only"}, "mU9ZbS08nDFxUL4Zv": {"name": "Own Race Only"}, "mD4we-sF6tX5d049E": {"name": "Psychic Healing"}, "mU8orpPb7fDtVxD8E": {"name": "Affects Self"}, "mdAAGhUzfNomFMn_j": {"name": "Cure Affliction"}, "mgHNTGnDq2ObZMx_0": {"name": "Affliction Only"}, "m40twSA4BCJYpwF0K": {"name": "Capped", "notes": "2 FP"}, "mGWVZMwNUorXAArUk": {"name": "Capped", "notes": "4 FP"}, "mOTv9TSx3GdcsMRm5": {"name": "Capped", "notes": "6 FP"}, "mzV8kBwl9T2Oollbz": {"name": "Capped", "notes": "8 FP"}, "mZ1m2W5pIacttKsxX": {"name": "Capped", "notes": "10 FP"}, "mcvqy7y52zr-WuJs_": {"name": "Empathic"}}}, "tGc0x1TVG2rRrdaN9": {"name": "Intuition", "tags": ["Advantage", "Mental"], "modifiers": {"mJQHdIAKYTRq7P3e4": {"name": "Inspired"}}}, "tPRo17mcVFBz0SA0u": {"name": "Oracle", "tags": ["Advantage", "Mental", "Supernatural"], "modifiers": {"m4gUbq_klnxvszIFL": {"name": "Inspired"}}}, "tAygbjsH2B01ZCLQQ": {"name": "Patron", "tags": ["Advantage", "Social"], "modifiers": {"m_GrVV9wz4iHlRBbA": {"name": "@Who: Individual with 150% of PC's starting points@"}, "mosal_-nRC33sQLZR": {"name": "@Who: Organization with assets of at least 1000 times starting wealth@"}, "mr9ewFDQoTIOv-LMx": {"name": "@Who: Individual with twice the PC's starting points@"}, "mrKQf5hu1iV0IXe6t": {"name": "@Who: Organization with assets of at least 10000 times starting wealth@"}, "mJ37Zs3rJlB8CwDaE": {"name": "@Who: An ultra-powerful individual@"}, "mvS3cWyQhP1Ub3Av5": {"name": "@Who: Organization with assets of at least 100000 times starting wealth@"}, "mbxpVnuiu8zT1AkrB": {"name": "@Who: Organization with assets of at least 1000000 times starting wealth@"}, "m84fvanU1CWN8dNUS": {"name": "@Who: A national government or giant multi-national organization@"}, "mTNTh53VPWMjxzYxn": {"name": "@Deity@"}, "mq_McZtzuoVaH5hz4": {"name": "Appears almost all the time", "notes": "15-"}, "mLe2SwHQebmwmfKlL": {"name": "Appears quite often", "notes": "12-"}, "mguqjcRROj3GpGPta": {"name": "Appears fairly often", "notes": "9-"}, "m0WlBHGtUfuylsUpU": {"name": "Appears quite rarely", "notes": "6-"}, "m2vTfExRR8SzPyPZA": {"name": "Equipment", "notes": "@Equipment worth no more than average starting wealth@"}, "mnYHDsIhYPumC_C5X": {"name": "Equipment", "notes": "@Equipment worth more than average starting wealth@"}, "m7zIAfMd4kDicesyI": {"name": "Highly Accessible"}, "m9Gixu-04gjW7EmXb": {"name": "Special Abilities", "notes": "@Extensive social or political power@"}, "munQGP66fPLSAvBXH": {"name": "Special Abilities", "notes": "Godly Power"}, "miWNtA9vfWApUHOFo": {"name": "Minimal Interventions"}, "mcY2xLzGdc6McdN0n": {"name": "Secret"}, "mzbSHwvgZiceX4pr2": {"name": "Unwilling"}, "mUocE3PZSzYl-Rv5g": {"name": "Favor"}}}, "tSUZQE8ApVcrdzegS": {"name": "Patron", "tags": ["Advantage", "Social"], "modifiers": {"mI3-hTKhbHI0pAAQn": {"name": "@Who: Individual with 150% of PC's starting points@"}, "msDXHS7CUH5ZoC3p2": {"name": "@Who: Organization with assets of at least 1000 times starting wealth@"}, "m4Bcxhw_-fLu3cAD4": {"name": "@Who: Individual with twice the PC's starting points@"}, "mC5emxPqBtx9fGksU": {"name": "@Who: Organization with assets of at least 10000 times starting wealth@"}, "mK75Cv96-ZorJrzTg": {"name": "@Who: An ultra-powerful individual@"}, "mlj2gMrXxL68vRa7j": {"name": "@Who: Organization with assets of at least 100000 times starting wealth@"}, "mx3jJyBg_kWpsJsKC": {"name": "@Who: Organization with assets of at least 1000000 times starting wealth@"}, "mDAtv2BjOJWxRAxgb": {"name": "@Who: A national government or giant multi-national organization@"}, "mUmIK9oMaguYH8637": {"name": "@Deity@"}, "mVkCQZh_uCee3IdaE": {"name": "Appears almost all the time", "notes": "15-"}, "mva0uGMmW5Caa2gIQ": {"name": "Appears quite often", "notes": "12-"}, "mdumyFPyOL70vkHDn": {"name": "Appears fairly often", "notes": "9-"}, "mAzu1BvIi2mAYVoBO": {"name": "Appears quite rarely", "notes": "6-"}, "mKHc7Dtzy5wnfG75n": {"name": "Equipment", "notes": "@Equipment worth no more than average starting wealth@"}, "m-g4_CEa7tL3P7LoH": {"name": "Equipment", "notes": "@Equipment worth more than average starting wealth@"}, "mP3z-djFnilfzg6qT": {"name": "Highly Accessible"}, "m4iuoXC6GBsXvxGiA": {"name": "Special Abilities", "notes": "@Extensive social or political power@"}, "mQcrekGK0xyuEWkjG": {"name": "Special Abilities", "notes": "Godly Power"}, "mor8AvFMZXqrIlh8x": {"name": "Minimal Interventions"}, "mNwNF07tuYd5o_-PA": {"name": "Secret"}, "mE8pJKsZQovl1XEC-": {"name": "Unwilling"}, "mOQ-XMWctuTZrZevJ": {"name": "Favor"}}}, "tPC0ojaCwpHLdJ8uM": {"name": "Resistant", "tags": ["Advantage", "Physical"], "modifiers": {"mnR4KIbK7bRg5UVAE": {"name": "@Very Common: Metabolic Hazards, etc.@"}, "m-rySxh9XCbX0Xqv9": {"name": "Evil supernatural Powers"}, "mMAAeZEKU7b1qh4X_": {"name": "@Occasional: Disease, Ingested Poison, etc.@"}, "m9tHHWpYGUu0Jlsog": {"name": "@Rare: Acceleration, Altitude Sickness, Bends, Seasickness, Space Sickness, Nanomachines, etc.@"}, "mgXOG13Vq-Qf6n86q": {"name": "Immunity"}, "mexZWqqzfVyjUA7gQ": {"name": "+8 to all HT rolls to resist"}, "mWq8bblxO3zYIvkQ1": {"name": "+3 to all HT rolls to resist"}}}, "tKmKoLTOabUtf6brs": {"name": "Resistant", "tags": ["Advantage", "Physical"], "modifiers": {"mR8ve6aq9jo335T30": {"name": "@Very Common: Metabolic Hazards, etc.@"}, "m29Vz-JTxMsAs9u2u": {"name": "Evil supernatural Powers"}, "mfOet7A-ug5dnpuGD": {"name": "@Occasional: Disease, Ingested Poison, etc.@"}, "m2XICNi3xVf5oXcwQ": {"name": "@Rare: Acceleration, Altitude Sickness, Bends, Seasickness, Space Sickness, Nanomachines, etc.@"}, "mrMP-0duNThRdsJNn": {"name": "Immunity"}, "mExkqPwG3LIji6vFR": {"name": "+8 to all HT rolls to resist"}, "mZZSkKzrcyYHjJiBk": {"name": "+3 to all HT rolls to resist"}}}, "tZfeB3C6-NI8-W9S6": {"name": "Spirit Empathy", "tags": ["Advantage", "Mental", "Supernatural"], "modifiers": {"mA8yjHej2ahYl4TPe": {"name": "Specialized", "notes": "@Type: Angels, Demons, Elementals, Faerie, Ghosts, etc.@"}, "mpAO61cQYWV2qOVOL": {"name": "Remote"}}}, "tpBor0xExIOltgAbo": {"name": "True Faith", "tags": ["Advantage", "Mental", "Supernatural"], "modifiers": {"mJw76Pfsptks16vJV": {"name": "Chosen", "notes": "@Deity@"}, "mZwBfoBERxyyYpEbl": {"name": "Turning"}}}}, "modifiers": {"mJF_A3rh96U-irGwI": {"name": "Power Modifier", "notes": "Holy"}}}}}, "ttvNpVHKE5wJsPaSt": {"name": "Clerical Investment", "tags": ["Advantage", "Social"]}, "tbOsh2YYhxLNRJWx_": {"name": "Power Investiture", "tags": ["Advantage", "Mental", "Supernatural"], "features": [{"name": {"qualifier": "Clerical"}}]}}}, "Te4UGXGw5NRf0yo6u": {"name": "Class Disadvantages", "children": {"TwnIJQtkWhsT9M7ED": {"name": "Choose One of:", "children": {"t1x82UWCfTQAja8tR": {"name": "Honesty", "tags": ["Disadvantage", "Mental"]}, "tM7gGtRZFFsV8EeHZ": {"name": "Sense of Duty", "tags": ["Disadvantage", "Mental"], "notes": "Good entities"}, "toldZaZbSg_kBmuA4": {"name": "Truthfulness", "tags": ["Disadvantage", "Mental"], "features": [{"name": {"qualifier": "fast talk"}}]}, "t0VGD5OZDlhKrvpRb": {"name": "Vow (Own no more than horse can carry)", "tags": ["Disadvantage", "Physical"]}, "tYO-ssfxqpAC0ZOo2": {"name": "Vow (Heal anyone who needs it)", "tags": ["Disadvantage", "Physical"]}, "T5tOYn_tytudIwmrK": {"name": "Or any form of Pacifism listed below. If greater than -10 then increase value of Power Modifier and adjust Holy Ability Costs.", "notes": "If the first required disadvatnage if worth more than -10 points, reduce points derived from optional disadvantages to balance the total", "children": {"tHLEjYNmCq0f5UdKQ": {"name": "Pacifism: Cannot Harm Innocents", "tags": ["Disadvantage", "Mental"], "modifiers": {"mzNUBvJsPZiMKYKbL": {"name": "Species-Specific"}}}, "tKUhy5ZP20eevgtIi": {"name": "Pacifism: Cannot Kill", "tags": ["Disadvantage", "Mental"], "modifiers": {"m9vc1AmdjfGhOsi6B": {"name": "Species-Specific"}}}, "tbu2TK7FEfXQxGDLn": {"name": "Pacifism: Self-Defense Only", "tags": ["Disadvantage", "Mental"], "modifiers": {"mOkOO5_K_DWCi3eJx": {"name": "Species-Specific"}}}, "t2i4Eu0ZRdIWAm7YR": {"name": "Pacifism: Total Nonviolence", "tags": ["Disadvantage", "Mental"], "modifiers": {"mWaefDiCdJZFdSxGm": {"name": "Species-Specific"}}}}}}}, "T3v8Av7th6fZU4TJh": {"name": "A further -25 Points chosen from:", "notes": "or any of the above lists", "children": {"tXXUSPkUHgn7Au6Tr": {"name": "Charitable", "tags": ["Disadvantage", "Mental"]}, "th1VnQXYe85PXqwGO": {"name": "Compulsive Generosity", "tags": ["Disadvantage", "Mental"], "prereqs": {"prereqs": [{"name": {"qualifier": "miserliness"}}]}}, "tcF6U_0hN6XIr7RIs": {"name": "Easy to Read", "tags": ["Disadvantage", "Mental"]}, "tCiXIX-uQMqH4gN3G": {"name": "Fat", "tags": ["Disadvantage", "Physical"], "notes": "+2 ST vs. knockback", "features": [{"name": {"qualifier": "disguise"}}, {"name": {"qualifier": "shadowing"}}, {"name": {"qualifier": "swimming"}}], "prereqs": {"prereqs": [{"qualifier": {"qualifier": 15}}]}}, "t84ZQLR6N3mEekVeQ": {"name": "Gluttony", "tags": ["Disadvantage", "Mental"]}, "twi59GTR4x5_HX4Lp": {"name": "Miserliness", "tags": ["Disadvantage", "Mental"]}, "tK5C9qUSWPAI6QJWX": {"name": "Overconfidence", "tags": ["Disadvantage", "Mental"]}, "t-7zPXS_8ivHqKFuW": {"name": "Overweight", "tags": ["Physical", "Quirk"], "notes": "+1 ST vs. knockback", "features": [{"name": {"qualifier": "disguise"}}, {"name": {"qualifier": "shadowing"}}, {"name": {"qualifier": "swimming"}}]}, "tFIYmuhsA-b_7DgUu": {"name": "Selfless", "tags": ["Disadvantage", "Mental"]}, "tnuo-UmylXyfzzg_k": {"name": "Sense of Duty", "tags": ["Disadvantage", "Mental"], "notes": "Adventuring companions"}, "t6CBnWLPOFypnw_OF": {"name": "Stubbornness", "tags": ["Disadvantage", "Mental"]}, "t2EqaswEg1Mn2uBdf": {"name": "Truthfulness", "tags": ["Disadvantage", "Mental"], "features": [{"name": {"qualifier": "fast talk"}}]}, "tpQe6bqEDUY_JStV7": {"name": "Weirdness Magnet", "tags": ["Disadvantage", "Mental", "Supernatural"], "modifiers": {"mIQIwVkOeG1UqsR8Y": {"name": "Origins Magnet"}}}}}, "T4l6fPvEvHnOanHUE": {"name": "Another -15 Points chosen from:", "notes": "or those above", "children": {"tgnK_vXEFVR9bZFil": {"name": "Disciplines of Faith (Mysticism)", "tags": ["Disadvantage", "Mental"]}, "tPVM85ZAqppZYRb5a": {"name": "Disciplines of Faith (Ritualism)", "tags": ["Disadvantage", "Mental"]}, "txGpFYD8o2xjrld6m": {"name": "Fanaticism", "tags": ["Disadvantage", "Mental"], "modifiers": {"mdcmKp7_MEbu9Y1WV": {"name": "Extreme"}}}, "tlJ8_H9msaoaZBc5H": {"name": "Intolerance (All other religions)", "tags": ["Disadvantage", "Mental"], "modifiers": {"m9wNG9gYJm7F9KhmP": {"name": "Scope: Common"}, "mJZ9l89nzsZWLGW61": {"name": "Scope: Occasional"}, "mnK2-bXXqdBRnXO_8": {"name": "Scope: Rare"}, "m2hSm_KWRrvrOLG_h": {"name": "Scope: Anyone unlike you"}}}, "tHs9YIqv9Zv-bpsxw": {"name": "Intolerance (Evil religions)", "tags": ["Disadvantage", "Mental"], "modifiers": {"m4-s5tR9F6xpfaogN": {"name": "Scope: Common"}, "mVYUuIT865-y1Wxng": {"name": "Scope: Occasional"}, "mzGmMERJRPYohOFlJ": {"name": "Scope: Rare"}, "m8_ZYu0w5hwbig9BU": {"name": "Scope: Anyone unlike you"}}}, "thg8um7mKAyJlmgMp": {"name": "Vow (Chastity)", "tags": ["Disadvantage", "Physical"]}, "tWyhns0a-z02BMMAX": {"name": "Vow (Vegetarianism)", "tags": ["Disadvantage", "Physical"]}, "tv7WNVi7fADJYche-": {"name": "Wealth (Poor)", "tags": ["Disadvantage", "Social"]}, "t33NbW105S8As2ouz": {"name": "Wealth (Struggling)", "tags": ["Disadvantage", "Social"]}}}}}}}}, "skills": {"SvW3JirP_I2cLcjlx": {"name": "Healing Cleric", "children": {"SZe7U0RAIcUIOQnjr": {"name": "Primary Skills", "children": {"sSzJEnCfedI1zDoA_": {"name": "Esoteric Medicine", "tags": ["Esoteric", "Medical"], "defaults": [{}]}, "sk857Z2HtwgDya2B3": {"name": "Exorcism", "tags": ["Magical", "Occult"], "defaults": [{}, {"name": "Religious Ritual"}, {"name": "Ritual Magic"}, {"name": "Theology"}]}, "Sin-5F0H0OXB2CbMo": {"name": "Choose One Melee Package", "children": {"SkPogWdjiHqaKHuLD": {"name": "Melee 1", "children": {"SNOwqPiAvHyQ1FYCD": {"name": "One of:", "children": {"s0CzakU07YGMR4ino": {"name": "Axe/Mace", "tags": ["Combat", "Melee Combat", "Weapon"], "defaults": [{}, {"name": "Two-Handed Axe/Mace"}, {"name": "Flail"}]}, "s78d2vHUX4i4N2QWu": {"name": "Broadsword", "tags": ["Combat", "Melee Combat", "Weapon"], "defaults": [{"name": "Force Sword"}, {"name": "Rapier"}, {"name": "Saber"}, {"name": "Shortsword"}, {"name": "Two-Handed Sword"}, {}]}}}, "sJ35By2wuADPsY9hB": {"name": "Shield", "tags": ["Combat", "Melee Combat", "Weapon"], "specialization": "Shield", "defaults": [{}]}}}, "S7ByaxMaIum2yXNvT": {"name": "Melee 2", "children": {"sSJXFGWTffyOBeWhS": {"name": "Flail", "tags": ["Combat", "Melee Combat", "Weapon"], "defaults": [{}, {"name": "Axe/Mace"}, {"name": "Two-Handed Flail"}]}, "sAjJ5SY9x8_TkkTmQ": {"name": "Shield", "tags": ["Combat", "Melee Combat", "Weapon"], "specialization": "Shield", "defaults": [{}]}}}, "SovldkVF6OZ232yx8": {"name": "Melee 3", "children": {"s5MOA1YY9V8NAooFL": {"name": "Staff", "tags": ["Combat", "Melee Combat", "Weapon"], "defaults": [{}, {"name": "Polearm"}, {"name": "Spear"}]}}}, "S1sZ8lLVboJDQLdxq": {"name": "Melee 4", "children": {"sbY0x22n_viMHDw19": {"name": "Knife", "tags": ["Combat", "Melee Combat", "Weapon"], "defaults": [{"name": "Force Sword"}, {"name": "Main-Gauche"}, {"name": "Shortsword"}, {}]}, "sGqwOaHFA0Dtfr5s2": {"name": "Brawling", "tags": ["Combat", "Melee Combat", "Weapon"], "features": [{"name": {"qualifier": "Brawling"}}]}}}}}, "S-ZGxAU8XzRh2THGZ": {"name": "Choose One of:", "children": {"sD89mUu9WFXWDArjH": {"name": "Innate Attack", "tags": ["Combat", "Ranged Combat", "Weapon"], "specialization": "Beam", "defaults": [{}, {"name": "Innate Attack"}]}, "sA0z9I_gSPgZMMlyS": {"name": "Innate Attack", "tags": ["Combat", "Ranged Combat", "Weapon"], "specialization": "Breath", "defaults": [{}, {"name": "Innate Attack"}]}, "s5m03QGCAU0zMnpnx": {"name": "Innate Attack", "tags": ["Combat", "Ranged Combat", "Weapon"], "specialization": "Gaze", "defaults": [{}, {"name": "Innate Attack"}]}, "smUdy6A8KYuoTYXys": {"name": "Innate Attack", "tags": ["Combat", "Ranged Combat", "Weapon"], "specialization": "Projectile", "defaults": [{}, {"name": "Innate Attack"}]}, "sN-CGHMbwFV7b7HQM": {"name": "Sling", "tags": ["Combat", "Ranged Combat", "Weapon"], "defaults": [{}]}, "sv8spB-s2Zb5_S6eE": {"name": "Throwing", "tags": ["Athletic", "Combat", "Ranged Combat", "Weapon"], "defaults": [{}, {"name": "Dropping"}]}}}}}, "S5JnZu0_RPItBuxEZ": {"name": "Secondary Skills", "children": {"sDIs2_vnSNxKPbY68": {"name": "Diagnosis", "tags": ["Medical"], "defaults": [{}, {"name": "First Aid"}, {"name": "Physician"}, {"name": "Veterinary"}]}, "szx_HSblNMP7mCkE7": {"name": "First Aid", "tags": ["Everyman", "Medical"], "defaults": [{}, {"name": "Esoteric Medicine"}, {"name": "Physician"}, {"name": "Veterinary"}]}, "sKbDlKBixUK2HB3cc": {"name": "Hidden Lore", "tags": ["Knowledge"], "specialization": "@Demons, Spirits or Undead@"}, "sO4B_Q8aAjOktsRUY": {"name": "Meditation", "tags": ["Esoteric"], "defaults": [{}, {"name": "Autohypnosis"}]}, "sDRsgtJEWzJyTZ-Y1": {"name": "Occultism", "tags": ["Magical", "Occult"], "defaults": [{}]}, "saIkJ_8eHOLOMhfyE": {"name": "Public Speaking", "tags": ["Business", "Scholarly", "Social"], "defaults": [{}, {"name": "Acting"}, {"name": "Performance"}, {"name": "Politics"}]}, "sLveCXq0V5zed5c-9": {"name": "Religious Ritual", "tags": ["Magical", "Occult"], "defaults": [{"name": "Ritual Magic"}, {"name": "Theology"}]}, "si0RqSn1jeVcFowGJ": {"name": "Surgery", "tags": ["Medical"], "prereqs": {"prereqs": [{"name": {"qualifier": "first aid"}}, {"name": {"qualifier": "physician"}}]}, "defaults": [{"name": "First Aid"}, {"name": "Physician"}, {"name": "Physiology"}, {"name": "Veterinary"}]}, "sYh-3bxpvaTec5BFi": {"name": "Teaching", "tags": ["Scholarly", "Social"], "defaults": [{}]}, "sFF8eeb06znZgrCWH": {"name": "Theology", "tags": ["Humanities", "Social Sciences"], "defaults": [{}, {"name": "Religious Ritual"}]}}}, "S7214w-YsbBwiG2Cx": {"name": "Background Skills", "children": {"SyzHN_IuKSOYrzPyF": {"name": "Five of:", "children": {"s-kUgM5YNiG-eCPZt": {"name": "Climbing", "tags": ["Athletic", "Criminal", "Exploration", "Outdoor", "Street"], "defaults": [{}]}, "s34KC2gaBemaQ0xKh": {"name": "Gesture", "tags": ["Social"], "defaults": [{}]}, "s70bvzcTsvJEAztBK": {"name": "Hiking", "tags": ["Athletic", "Exploration", "Outdoor"], "defaults": [{}]}, "sAg7SKHyHcKq-MS9y": {"name": "Observation", "tags": ["Criminal", "Military", "Police", "Spy", "Street"], "defaults": [{}, {"name": "Shadowing"}]}, "s8saXMjQ7qHSRko2V": {"name": "Panhandling", "tags": ["Criminal", "Social", "Street"], "defaults": [{}, {"name": "Fast Talk"}, {"name": "Public Speaking"}]}, "sQdTLy45EE0LI9_Uh": {"name": "Research", "tags": ["Scholarly", "Spy"], "notes": "When below TL8", "prereqs": {"prereqs": [{"name": {"qualifier": "Language"}, "notes": {"qualifier": "Written (Broken)"}}, {"name": {"qualifier": "Language"}, "notes": {"qualifier": "Written (Native)"}}, {"name": {"qualifier": "Language"}, "notes": {"qualifier": "Written (Accented)"}}]}, "defaults": [{}, {"name": "Writing"}]}, "sAyKa5zpk4tPU11qz": {"name": "Savoir-Faire", "tags": ["Business", "Knowledge", "Social"], "specialization": "High Society", "defaults": [{}, {"name": "Savoir-Faire", "specialization": "Servant"}]}, "sJ7IImodm7V2xGiwn": {"name": "Scrounging", "tags": ["Criminal", "Street"], "defaults": [{}]}, "svXrPnK-Cfk5bcVWF": {"name": "Search", "tags": ["Police", "Spy"], "defaults": [{}, {"name": "Criminology"}]}, "sDGi91HN6K4zG3Bb4": {"name": "Stealth", "tags": ["Criminal", "Police", "Spy", "Street"], "defaults": [{}, {}]}, "sUjjGV5C7MjDH75Nc": {"name": "Writing", "tags": ["Arts", "Entertainment", "Scholarly"], "defaults": [{}]}}}}}}}}, "spells": {"PiKn_vJM-Ft_5Qp6Y": {"name": "Healing Cleric", "children": {"PbjRMBDtpByhdU163": {"name": "Choose 20 of:", "children": {"PtM5vKajZBo9Z8F6U": {"name": "Power Investiture", "tags": ["Clerical"], "notes": "1", "children": {"pESmJfBqDUatLIJ_Z": {"name": "Minor healing", "tags": ["Clerical"], "power_source": "Arcane", "spell_class": "Regular", "casting_time": "1 sec", "duration": "Permanent", "casting_cost": "1-3", "maintenance_cost": "-", "college": ["Clerical"], "prereqs": {"prereqs": [{"name": {"qualifier": "Power Investiture"}}]}}, "Pc1sj3DCM-skNOfah": {"name": "And choose from:", "children": {"pSZUTelEIZisJ38DS": {"name": "Aura", "tags": ["Clerical"], "power_source": "Arcane", "spell_class": "Info", "casting_time": "1 sec", "duration": "Instant", "casting_cost": "3", "maintenance_cost": "-", "college": ["Clerical"], "prereqs": {"prereqs": [{"name": {"qualifier": "Power Investiture"}}]}}, "pj8rb1dVx41SsNLup": {"name": "Awaken", "tags": ["Clerical"], "power_source": "Arcane", "spell_class": "Area", "casting_time": "1 sec", "duration": "Permanent", "casting_cost": "1", "maintenance_cost": "-", "college": ["Clerical"], "prereqs": {"prereqs": [{"name": {"qualifier": "Power Investiture"}}]}}, "p_cfpmOI-UvGJ_mRH": {"name": "Beast Soother", "tags": ["Animal"], "power_source": "Arcane", "spell_class": "Regular", "casting_time": "1 sec", "duration": "Permanent", "casting_cost": "1 to 3", "maintenance_cost": "-", "college": ["Clerical"], "prereqs": {"prereqs": [{"name": {"qualifier": "Power Investiture"}}]}}, "pM1JbFn32gh_gOk-T": {"name": "Body-Reading", "tags": ["Clerical"], "power_source": "Arcane", "spell_class": "Info", "casting_time": "30 sec", "duration": "-", "casting_cost": "2", "maintenance_cost": "-", "college": ["Clerical"], "prereqs": {"prereqs": [{"name": {"qualifier": "Power Investiture"}}]}}, "p-JvjPDsJFjZCTL5g": {"name": "Bravery", "tags": ["Clerical"], "power_source": "Arcane", "spell_class": "Area", "casting_time": "1 sec", "duration": "1 hr", "casting_cost": "2", "maintenance_cost": "-", "college": ["Clerical"], "prereqs": {"prereqs": [{"name": {"qualifier": "Power Investiture"}}]}}, "pyV56-_ZrdHdNie9s": {"name": "Clean", "tags": ["Clerical"], "power_source": "Arcane", "spell_class": "Area", "casting_time": "1 sec", "duration": "Permanent", "casting_cost": "2", "maintenance_cost": "-", "college": ["Clerical"], "prereqs": {"prereqs": [{"name": {"qualifier": "Power Investiture"}}]}}, "prq98xCycUEWXPV0K": {"name": "Cleansing", "tags": ["Clerical"], "power_source": "Arcane", "spell_class": "Regular", "casting_time": "2 sec", "duration": "Permanent", "casting_cost": "2/4/6", "maintenance_cost": "-", "college": ["Clerical"], "prereqs": {"prereqs": [{"name": {"qualifier": "Power Investiture"}}]}}, "p4atBHVkqGGYej2NA": {"name": "Coolness", "tags": ["Clerical"], "power_source": "Arcane", "spell_class": "Regular", "casting_time": "10 sec", "duration": "1 hour", "casting_cost": "2", "maintenance_cost": "1", "college": ["Clerical"], "prereqs": {"prereqs": [{"name": {"qualifier": "Power Investiture"}}]}}, "pLL5XYgwbe2cTiz9H": {"name": "Detect Magic", "tags": ["Clerical"], "power_source": "Arcane", "spell_class": "Regular", "casting_time": "5 sec", "duration": "Instant", "casting_cost": "2", "maintenance_cost": "-", "college": ["Clerical"], "prereqs": {"prereqs": [{"name": {"qualifier": "Power Investiture"}}]}}, "pGnPK8oaAcazxP3vJ": {"name": "Detect Poison", "tags": ["Clerical"], "power_source": "Arcane", "spell_class": "Area-Info", "casting_time": "2 sec", "duration": "-", "casting_cost": "2", "maintenance_cost": "-", "college": ["Clerical"], "prereqs": {"prereqs": [{"name": {"qualifier": "Power Investiture"}}]}}, "pUxw-jodTpG8m1viX": {"name": "Final Rest", "tags": ["Clerical"], "power_source": "Arcane", "spell_class": "Regular", "casting_time": "10 min", "duration": "Permanent", "casting_cost": "20", "maintenance_cost": "-", "college": ["Clerical"], "prereqs": {"prereqs": [{"name": {"qualifier": "Power Investiture"}}]}}, "pk5LY8sdPNCM5ZC3G": {"name": "Healing Slumber", "tags": ["Clerical"], "power_source": "Arcane", "spell_class": "Regular", "casting_time": "30 sec", "duration": "Up to 8 hrs", "casting_cost": "6 or 10", "maintenance_cost": "-", "college": ["Clerical"], "prereqs": {"prereqs": [{"name": {"qualifier": "Power Investiture"}}]}}, "ptxIQ5BOFeoXQgy20": {"name": "Lend Energy", "tags": ["Clerical"], "power_source": "Arcane", "spell_class": "Regular", "casting_time": "1 sec", "duration": "Permanent", "casting_cost": "1/pt", "maintenance_cost": "-", "college": ["Clerical"], "prereqs": {"prereqs": [{"name": {"qualifier": "Power Investiture"}}]}}, "poA81MH6zTnsSadY_": {"name": "Lend Vitality", "tags": ["Clerical"], "power_source": "Arcane", "spell_class": "Regular", "casting_time": "1 sec", "duration": "1 Hour", "casting_cost": "1/pt", "maintenance_cost": "-", "college": ["Clerical"], "prereqs": {"prereqs": [{"name": {"qualifier": "Power Investiture"}}]}}, "pZSYjtoXi0fBNbokK": {"name": "Might", "tags": ["Clerical"], "power_source": "Arcane", "spell_class": "Regular", "casting_time": "1 sec", "duration": "1 min", "casting_cost": "2/+ST", "maintenance_cost": "Same", "college": ["Clerical"], "prereqs": {"prereqs": [{"name": {"qualifier": "Power Investiture"}}]}}, "pR6hFJ_vU1MTKnOeq": {"name": "Purify Air", "tags": ["Clerical"], "power_source": "Arcane", "spell_class": "Area", "casting_time": "1 sec", "duration": "Instant", "casting_cost": "1", "maintenance_cost": "-", "college": ["Clerical"], "prereqs": {"prereqs": [{"name": {"qualifier": "Power Investiture"}}]}}, "pJSg1P_Ug-Le47hkS": {"name": "Purify Water", "tags": ["Clerical"], "power_source": "Arcane", "spell_class": "Special", "casting_time": "5-10/gal#", "duration": "Permanent", "casting_cost": "1/gal", "maintenance_cost": "-", "college": ["Clerical"], "prereqs": {"prereqs": [{"name": {"qualifier": "Power Investiture"}}]}}, "pVYLInBafXc08l20k": {"name": "Recover Energy", "tags": ["Clerical"], "power_source": "Arcane", "spell_class": "Special", "casting_time": "1 sec", "duration": "Special", "casting_cost": "0", "maintenance_cost": "0", "college": ["Clerical"], "prereqs": {"prereqs": [{"name": {"qualifier": "Power Investiture"}}]}}, "pIVKOVf1EZIgB6-1V": {"name": "Resist Fire", "tags": ["Clerical"], "power_source": "Arcane", "spell_class": "Regular", "casting_time": "1 sec", "duration": "1 min", "casting_cost": "2#", "maintenance_cost": "Half", "college": ["Clerical"], "prereqs": {"prereqs": [{"name": {"qualifier": "Power Investiture"}}]}}, "pXet3e7U4KFDJW-LA": {"name": "Sense Life", "tags": ["Clerical"], "power_source": "Arcane", "spell_class": "Info/Area", "casting_time": "1 sec", "duration": "Instant", "casting_cost": "1/2", "maintenance_cost": "-", "college": ["Clerical"], "prereqs": {"prereqs": [{"name": {"qualifier": "Power Investiture"}}]}}, "pZZsuUW0GIrEwEcfz": {"name": "Sense Spirit", "tags": ["Clerical"], "power_source": "Arcane", "spell_class": "Info/Area", "casting_time": "1 sec", "duration": "Instant", "casting_cost": "1/2 (min 1)", "maintenance_cost": "-", "college": ["Clerical"], "prereqs": {"prereqs": [{"name": {"qualifier": "Power Investiture"}}]}}, "puoQ5PhI3xNVPsJw5": {"name": "Share Vitality", "tags": ["Clerical"], "power_source": "Arcane", "spell_class": "Regular", "casting_time": "1 sec/HP", "duration": "Permanent", "casting_cost": "None", "maintenance_cost": "-", "college": ["Clerical"], "prereqs": {"prereqs": [{"name": {"qualifier": "Power Investiture"}}]}}, "pm2AuPG_Q2-07yPYC": {"name": "Stop Bleeding", "tags": ["Clerical"], "power_source": "Arcane", "spell_class": "Regular", "casting_time": "1 sec", "duration": "Permanent", "casting_cost": "1 or 10", "maintenance_cost": "-", "college": ["Clerical"], "prereqs": {"prereqs": [{"name": {"qualifier": "Power Investiture"}}]}}, "pCf9Frq4Fd8O3VTVL": {"name": "Test Food", "tags": ["Clerical"], "power_source": "Arcane", "spell_class": "Info", "casting_time": "1 sec", "duration": "Instant", "casting_cost": "1 or 3", "maintenance_cost": "-", "college": ["Clerical"], "prereqs": {"prereqs": [{"name": {"qualifier": "Power Investiture"}}]}}, "p3YJPs9wR1H6BkCdk": {"name": "Stop Spasm", "tags": ["Body Control", "Healing"], "power_source": "Arcane", "spell_class": "Regular", "casting_time": "1 sec", "duration": "Permanent", "casting_cost": "1", "maintenance_cost": "-", "college": ["Clerical"], "prereqs": {"prereqs": [{"name": {"qualifier": "Power Investiture"}}]}}, "pFxK6ZuvYrWanhLNZ": {"name": "Umbrella", "tags": ["Clerical"], "power_source": "Arcane", "spell_class": "Regular", "casting_time": "2 sec", "duration": "10 min", "casting_cost": "1", "maintenance_cost": "1", "college": ["Clerical"], "prereqs": {"prereqs": [{"name": {"qualifier": "Power Investiture"}}]}}, "pdj-UJDZMTtgGZHm_": {"name": "Vigor", "tags": ["Clerical"], "power_source": "Arcane", "spell_class": "Regular", "casting_time": "1 sec", "duration": "1 min", "casting_cost": "2/+HT", "maintenance_cost": "Same", "college": ["Clerical"], "prereqs": {"prereqs": [{"name": {"qualifier": "Power Investiture"}}]}}, "ptTjZZDgjTRbWryQk": {"name": "Warmth", "tags": ["Clerical"], "power_source": "Arcane", "spell_class": "Regular", "casting_time": "10 sec", "duration": "1 hr", "casting_cost": "2", "maintenance_cost": "1", "college": ["Clerical"], "prereqs": {"prereqs": [{"name": {"qualifier": "Power Investiture"}}]}}}}}}, "Pa5yrtEqjjGwkeJp4": {"name": "Power Investiture", "tags": ["Clerical"], "notes": "2", "children": {"p3oysv8pWxjSeJivN": {"name": "Relieve Sickness", "tags": ["Clerical"], "power_source": "Arcane", "spell_class": "Regular", "casting_time": "10 sec", "duration": "10 min", "casting_cost": "2", "maintenance_cost": "-", "college": ["Clerical"], "prereqs": {"prereqs": [{"name": {"qualifier": "Power Investiture"}}]}}, "PUuNt8TNriKfAtr3H": {"name": "And choose from:", "children": {"piN0pwvYddsZhO3OG": {"name": "Armor", "tags": ["Clerical"], "power_source": "Arcane", "spell_class": "Regular", "casting_time": "1 sec", "duration": "1 min", "casting_cost": "2 per DR", "maintenance_cost": "Half", "college": ["Clerical"], "prereqs": {"prereqs": [{"name": {"qualifier": "Power Investiture"}}]}}, "p9dGu_2c3vkkXVbiE": {"name": "Create Water", "tags": ["Clerical"], "power_source": "Arcane", "spell_class": "Regular", "casting_time": "1 sec", "duration": "Permanent", "casting_cost": "2/gal", "maintenance_cost": "-", "college": ["Clerical"], "prereqs": {"prereqs": [{"name": {"qualifier": "Power Investiture"}}]}}, "pFLISeUqJdqB5tALH": {"name": "Light", "tags": ["Clerical"], "power_source": "Arcane", "spell_class": "Regular", "casting_time": "1 sec", "duration": "1 min", "casting_cost": "1", "maintenance_cost": "1", "college": ["Clerical"], "prereqs": {"prereqs": [{"name": {"qualifier": "Power Investiture"}}]}}, "psp-bmxoSP3jQo1yS": {"name": "Major Healing", "tags": ["Clerical"], "power_source": "Arcane", "spell_class": "Regular", "casting_time": "1 sec", "duration": "Permanent", "casting_cost": "1-4", "maintenance_cost": "-", "college": ["Clerical"], "prereqs": {"prereqs": [{"name": {"qualifier": "Power Investiture"}}]}}, "pQArMerhlrf0moEOQ": {"name": "Peaceful Sleep", "tags": ["Clerical"], "power_source": "Arcane", "spell_class": "Regular", "casting_time": "30 sec", "duration": "8 hrs", "casting_cost": "4", "maintenance_cost": "-", "college": ["Clerical"], "prereqs": {"prereqs": [{"name": {"qualifier": "Power Investiture"}}]}}, "plZGfWC0sZ_svf8KI": {"name": "Purify Food", "tags": ["Clerical"], "power_source": "Arcane", "spell_class": "Regular", "casting_time": "1 sec", "duration": "Permanent", "casting_cost": "1/lb", "maintenance_cost": "-", "college": ["Clerical"], "prereqs": {"prereqs": [{"name": {"qualifier": "Power Investiture"}}]}}, "pHfBmWn7Dr2okqXv3": {"name": "Relieve Paralysis", "tags": ["Clerical"], "power_source": "Arcane", "spell_class": "Regular", "casting_time": "10 sec", "duration": "1 min", "casting_cost": "Varies", "maintenance_cost": "Same", "college": ["Clerical"], "prereqs": {"prereqs": [{"name": {"qualifier": "Power Investiture"}}]}}, "pGgyOUWyPbL3kRJ2z": {"name": "Remove Contagion", "tags": ["Clerical"], "power_source": "Arcane", "spell_class": "Area", "casting_time": "2 sec", "duration": "Permanent", "casting_cost": "3", "maintenance_cost": "-", "college": ["Clerical"], "prereqs": {"prereqs": [{"name": {"qualifier": "Power Investiture"}}]}}, "pYfVBcXOZQGIHujwG": {"name": "Resist Cold", "tags": ["Clerical"], "power_source": "Arcane", "spell_class": "Regular", "casting_time": "1 sec", "duration": "1 min", "casting_cost": "2", "maintenance_cost": "Half", "college": ["Clerical"], "prereqs": {"prereqs": [{"name": {"qualifier": "Power Investiture"}}]}}, "pLHQ7R_MorPNOa-hK": {"name": "Resist Disease", "tags": ["Clerical"], "power_source": "Arcane", "spell_class": "Regular", "casting_time": "10 sec", "duration": "1 hr", "casting_cost": "4", "maintenance_cost": "3", "college": ["Clerical"], "prereqs": {"prereqs": [{"name": {"qualifier": "Power Investiture"}}]}}, "pU33fH5JZJgQeH9WO": {"name": "Resist Pain", "tags": ["Clerical"], "power_source": "Arcane", "spell_class": "Regular", "casting_time": "1 sec", "duration": "1 min", "casting_cost": "4", "maintenance_cost": "2", "college": ["Clerical"], "prereqs": {"prereqs": [{"name": {"qualifier": "Power Investiture"}}]}}, "pF7ZFwRuuARrxKwV4": {"name": "Resist Poison", "tags": ["Clerical"], "power_source": "Arcane", "spell_class": "Regular", "casting_time": "10 sec", "duration": "1 Hour", "casting_cost": "4", "maintenance_cost": "3", "college": ["Clerical"], "prereqs": {"prereqs": [{"name": {"qualifier": "Power Investiture"}}]}}, "p8znaMP0N0lCANMq3": {"name": "Restore Hearing", "tags": ["Clerical"], "power_source": "Arcane", "spell_class": "Regular", "casting_time": "5 sec", "duration": "1 Hour", "casting_cost": "Varies", "maintenance_cost": "Half", "college": ["Clerical"], "prereqs": {"prereqs": [{"name": {"qualifier": "Power Investiture"}}]}}, "ptmWNN638vGOT_R3f": {"name": "Restore Memory", "tags": ["Clerical"], "power_source": "Arcane", "spell_class": "Regular", "casting_time": "10 sec", "duration": "Permanent", "casting_cost": "3", "maintenance_cost": "-", "college": ["Clerical"], "prereqs": {"prereqs": [{"name": {"qualifier": "Power Investiture"}}]}}, "pgj3HDz74mHzpG3NM": {"name": "Restore Sight", "tags": ["Clerical"], "power_source": "Arcane", "spell_class": "Regular", "casting_time": "5 sec", "duration": "1 hour", "casting_cost": "Varies", "maintenance_cost": "Half", "college": ["Clerical"], "prereqs": {"prereqs": [{"name": {"qualifier": "Power Investiture"}}]}}, "p9CUqKSBEdighPGNg": {"name": "Restore Speech", "tags": ["Clerical"], "power_source": "Arcane", "spell_class": "Regular", "casting_time": "5 sec", "duration": "1 Hour", "casting_cost": "5", "maintenance_cost": "3", "college": ["Clerical"], "prereqs": {"prereqs": [{"name": {"qualifier": "Power Investiture"}}]}}, "pVv8onZtVi_s64sBv": {"name": "Shield", "tags": ["Clerical"], "power_source": "Arcane", "spell_class": "Regular", "casting_time": "1 sec", "duration": "1 min", "casting_cost": "2 per DB", "maintenance_cost": "Half", "college": ["Clerical"], "prereqs": {"prereqs": [{"name": {"qualifier": "Power Investiture"}}]}}, "ppHf7HHvNV_C1mZMA": {"name": "Silence", "tags": ["Clerical"], "power_source": "Arcane", "spell_class": "Area", "casting_time": "1 sec", "duration": "1 min", "casting_cost": "2", "maintenance_cost": "Half", "college": ["Clerical"], "prereqs": {"prereqs": [{"name": {"qualifier": "Power Investiture"}}]}}, "pKGUpK8lTxsMK3Vlw": {"name": "Soilproof", "tags": ["Clerical"], "power_source": "Arcane", "spell_class": "Regular", "casting_time": "2 sec", "duration": "10 min", "casting_cost": "2", "maintenance_cost": "1", "college": ["Clerical"], "prereqs": {"prereqs": [{"name": {"qualifier": "Power Investiture"}}]}}, "peCkF52mS5-coMsLG": {"name": "Strike Numb", "tags": ["Body Control"], "power_source": "Arcane", "spell_class": "Regular", "casting_time": "1 sec", "duration": "10 sec", "casting_cost": "3", "maintenance_cost": "1", "college": ["Clerical"], "prereqs": {"prereqs": [{"name": {"qualifier": "Power Investiture"}}]}}}}}}, "PKtjhpmkWzv33CQvW": {"name": "Power Investiture", "tags": ["Clerical"], "notes": "3", "children": {"pLxCWL-RUDbPBafA4": {"name": "Cure Disease", "tags": ["Clerical"], "power_source": "Arcane", "spell_class": "Regular", "casting_time": "10 min", "duration": "Permanent", "casting_cost": "4", "maintenance_cost": "-", "college": ["Clerical"], "prereqs": {"prereqs": [{"name": {"qualifier": "Power Investiture"}}]}}, "Po8nQ4zSxBvjrTl16": {"name": "And choose from:", "children": {"pjQXZTUY3PpcQbCmA": {"name": "Command", "tags": ["Clerical"], "power_source": "Arcane", "spell_class": "Blocking", "casting_time": "1 sec", "duration": "Instant", "casting_cost": "2", "maintenance_cost": "-", "college": ["Clerical"], "prereqs": {"prereqs": [{"name": {"qualifier": "Power Investiture"}}]}}, "pBxVQwWTqTtbyJX6Q": {"name": "Continual Light", "tags": ["Clerical"], "power_source": "Arcane", "spell_class": "Regular", "casting_time": "1 sec", "duration": "2d days", "casting_cost": "2 moon, 4 torch, 6 day", "maintenance_cost": "-", "college": ["Clerical"], "prereqs": {"prereqs": [{"name": {"qualifier": "Power Investiture"}}]}}, "pGi2mjf3cl-q-_3K7": {"name": "Create Food", "tags": ["Clerical"], "power_source": "Arcane", "spell_class": "Regular", "casting_time": "30 sec", "duration": "Permanent", "casting_cost": "Varies", "maintenance_cost": "-", "college": ["Clerical"], "prereqs": {"prereqs": [{"name": {"qualifier": "Power Investiture"}}]}}, "p1fqXJVqBV920-7kn": {"name": "Dispel Possession", "tags": ["Clerical"], "power_source": "Arcane", "spell_class": "Regular", "casting_time": "10 sec", "duration": "Instant", "casting_cost": "10", "maintenance_cost": "-", "college": ["Clerical"], "prereqs": {"prereqs": [{"name": {"qualifier": "Power Investiture"}}]}}, "ppO5imcv5Fewjv8Hp": {"name": "Great Healing", "tags": ["Clerical"], "power_source": "Arcane", "spell_class": "Regular", "casting_time": "1 min", "duration": "Permanent", "casting_cost": "20", "maintenance_cost": "-", "college": ["Clerical"], "prereqs": {"prereqs": [{"name": {"qualifier": "Power Investiture"}}]}}, "puIYzwyWAxrjzco59": {"name": "Heal Plant", "tags": ["Plant"], "power_source": "Arcane", "spell_class": "Area", "casting_time": "1 Min", "duration": "Permanent", "casting_cost": "3", "maintenance_cost": "-", "college": ["Clerical"], "prereqs": {"prereqs": [{"name": {"qualifier": "Power Investiture"}}]}}, "pyx05Z7yYWkd-aiCX": {"name": "Magic Resistance", "tags": ["Clerical"], "power_source": "Arcane", "spell_class": "Regular", "casting_time": "3 sec", "duration": "1 min", "casting_cost": "1-5", "maintenance_cost": "Same", "college": ["Clerical"], "prereqs": {"prereqs": [{"name": {"qualifier": "Power Investiture"}}]}}, "pnWzOsssckIeY0s5b": {"name": "Neutralize Poison", "tags": ["Clerical"], "power_source": "Arcane", "spell_class": "Regular", "casting_time": "30 sec", "duration": "Permanent", "casting_cost": "5", "maintenance_cost": "-", "college": ["Clerical"], "prereqs": {"prereqs": [{"name": {"qualifier": "Power Investiture"}}]}}, "pk98E-d-kukN82psY": {"name": "Relieve Madness", "tags": ["Clerical"], "power_source": "Arcane", "spell_class": "Regular", "casting_time": "10 sec", "duration": "10 min", "casting_cost": "2", "maintenance_cost": "-", "college": ["Clerical"], "prereqs": {"prereqs": [{"name": {"qualifier": "Power Investiture"}}]}}, "p-ghqB459PeFDOCqQ": {"name": "Repel Spirits", "tags": ["Clerical"], "power_source": "Arcane", "spell_class": "Area", "casting_time": "10 sec", "duration": "1 hr", "casting_cost": "4", "maintenance_cost": "Half", "college": ["Clerical"], "prereqs": {"prereqs": [{"name": {"qualifier": "Power Investiture"}}]}}, "psgoaijxFG6y8AOsH": {"name": "Resist Acid", "tags": ["Clerical"], "power_source": "Arcane", "spell_class": "Regular", "casting_time": "1 sec", "duration": "1 min", "casting_cost": "2 or 6", "maintenance_cost": "Half", "college": ["Clerical"], "prereqs": {"prereqs": [{"name": {"qualifier": "Power Investiture"}}]}}, "p1UxMxKArRVIiSIlc": {"name": "Resist Lightning", "tags": ["Clerical"], "power_source": "Arcane", "spell_class": "Regular", "casting_time": "1 sec", "duration": "1 min", "casting_cost": "2", "maintenance_cost": "1", "college": ["Clerical"], "prereqs": {"prereqs": [{"name": {"qualifier": "Power Investiture"}}]}}, "pAa3re9hwaaYWHCYw": {"name": "Restoration", "tags": ["Clerical"], "power_source": "Arcane", "spell_class": "Regular", "casting_time": "1 min", "duration": "Permanent", "casting_cost": "15", "maintenance_cost": "-", "college": ["Clerical"], "prereqs": {"prereqs": [{"name": {"qualifier": "Power Investiture"}}]}}, "pi0ch2DLzaCVbHuf7": {"name": "Spasm", "tags": ["Body Control"], "power_source": "Arcane", "spell_class": "Regular", "casting_time": "1 sec", "duration": "Instant", "casting_cost": "2", "maintenance_cost": "-", "college": ["Clerical"], "prereqs": {"prereqs": [{"name": {"qualifier": "Power Investiture"}}]}}, "pLa8UJzBZio5j3_gi": {"name": "Stone to Flesh", "tags": ["Clerical"], "power_source": "Arcane", "spell_class": "Regular", "casting_time": "5 sec", "duration": "Permanent", "casting_cost": "10", "maintenance_cost": "-", "college": ["Clerical"], "prereqs": {"prereqs": [{"name": {"qualifier": "Power Investiture"}}]}}, "poxAv_f54fXByGNiD": {"name": "Stop Paralysis", "tags": ["Clerical"], "power_source": "Arcane", "spell_class": "Regular", "casting_time": "1 sec", "duration": "Permanent", "casting_cost": "1 or 2", "maintenance_cost": "-", "college": ["Clerical"], "prereqs": {"prereqs": [{"name": {"qualifier": "Power Investiture"}}]}}, "pvYSP0NdA069-ThSL": {"name": "Strengthen Will", "tags": ["Clerical"], "power_source": "Arcane", "spell_class": "Regular", "casting_time": "1 sec", "duration": "1 min", "casting_cost": "1/pt of Will increase", "maintenance_cost": "Half", "college": ["Clerical"], "prereqs": {"prereqs": [{"name": {"qualifier": "Power Investiture"}}]}}, "pSdt47Ijcmh41t6NX": {"name": "Suspended Animation", "tags": ["Clerical"], "power_source": "Arcane", "spell_class": "Regular", "casting_time": "30 sec", "duration": "Until Awakened", "casting_cost": "6", "maintenance_cost": "-", "college": ["Clerical"], "prereqs": {"prereqs": [{"name": {"qualifier": "Power Investiture"}}]}}, "pXfX9n5ExXL2cdY32": {"name": "Turn Spirit", "tags": ["Clerical"], "power_source": "Arcane", "spell_class": "Regular", "casting_time": "1 sec", "duration": "10 sec", "casting_cost": "4", "maintenance_cost": "2", "college": ["Clerical"], "prereqs": {"prereqs": [{"name": {"qualifier": "Power Investiture"}}]}}, "pRFYGszxObfHQteIg": {"name": "Turn Zombie", "tags": ["Clerical"], "power_source": "Arcane", "spell_class": "Area", "casting_time": "4 sec", "duration": "Turned undead will avoid caster for 1 day", "casting_cost": "2", "maintenance_cost": "-", "college": ["Clerical"], "prereqs": {"prereqs": [{"name": {"qualifier": "Power Investiture"}}]}}}}}}, "PSPFCEO6J0UZf1TW5": {"name": "if chosen from advantages", "children": {"PTfbuclFbxF7I_Zyj": {"name": "Power Investiture", "tags": ["Clerical"], "notes": "4", "children": {"pqCnJ5gXYDTfcERVO": {"name": "Affect Spirits", "tags": ["Clerical"], "power_source": "Arcane", "spell_class": "Regular", "casting_time": "2 sec", "duration": "1 min", "casting_cost": "4", "maintenance_cost": "2", "college": ["Clerical"], "prereqs": {"prereqs": [{"name": {"qualifier": "Power Investiture"}}]}}, "pkvbGChcU2hgMZh53": {"name": "Astral Block", "tags": ["Clerical"], "power_source": "Arcane", "spell_class": "Area", "casting_time": "2 sec", "duration": "10 min", "casting_cost": "Varies", "maintenance_cost": "Half", "college": ["Clerical"], "prereqs": {"prereqs": [{"name": {"qualifier": "Power Investiture"}}]}}, "pOvUrs1_UqHPpAu3f": {"name": "Astral Vision", "tags": ["Clerical"], "power_source": "Arcane", "spell_class": "Regular", "casting_time": "1 sec", "duration": "1 min", "casting_cost": "4", "maintenance_cost": "2", "college": ["Clerical"], "prereqs": {"prereqs": [{"name": {"qualifier": "Power Investiture"}}]}}, "pXj2jYCLKUVAn3rZP": {"name": "Banish", "tags": ["Clerical"], "power_source": "Arcane", "spell_class": "Special", "casting_time": "5 sec", "duration": "Permanent", "casting_cost": "1 per 10 CP", "maintenance_cost": "-", "college": ["Clerical"], "prereqs": {"prereqs": [{"name": {"qualifier": "Power Investiture"}}]}}, "pHY6I-ouvh8x4VTyz": {"name": "Bless", "tags": ["Clerical"], "power_source": "Arcane", "spell_class": "Regular", "casting_time": "min=cost", "duration": "Varies", "casting_cost": "10/50/500", "maintenance_cost": "-", "college": ["Clerical"], "prereqs": {"prereqs": [{"name": {"qualifier": "Power Investiture"}}]}}, "pWyuv9mf0ZmpQT9_v": {"name": "Command Spirit (@spirit@)", "tags": ["Clerical"], "power_source": "Arcane", "spell_class": "Regular", "casting_time": "2 sec", "duration": "1 min", "casting_cost": "1 per 10 CP", "maintenance_cost": "Half", "college": ["Clerical"], "prereqs": {"prereqs": [{"name": {"qualifier": "Power Investiture"}}]}}, "pUHOzTaz19NzwwZIc": {"name": "Compel Truth", "tags": ["Clerical"], "power_source": "Arcane", "spell_class": "Info", "casting_time": "1 sec", "duration": "5 min", "casting_cost": "4", "maintenance_cost": "2", "college": ["Clerical"], "prereqs": {"prereqs": [{"name": {"qualifier": "Power Investiture"}}]}}, "pMyvX6BsOuKAA3_-2": {"name": "Dispel Magic", "tags": ["Clerical"], "power_source": "Arcane", "spell_class": "Area", "casting_time": "sec=cost", "duration": "Permanent", "casting_cost": "3", "maintenance_cost": "-", "college": ["Clerical"], "prereqs": {"prereqs": [{"name": {"qualifier": "Power Investiture"}}]}}, "p-aUYWmgT8mOO6pQx": {"name": "Divination: Astrology", "tags": ["Clerical"], "power_source": "Arcane", "spell_class": "Info", "casting_time": "1 hr", "duration": "Instant", "casting_cost": "10", "maintenance_cost": "-", "college": ["Clerical"], "prereqs": {"prereqs": [{"name": {"qualifier": "Power Investiture"}}]}}, "pTvfrpx3AH-jGIYmj": {"name": "Divination: Augury", "tags": ["Clerical"], "power_source": "Arcane", "spell_class": "Info", "casting_time": "1 hr", "duration": "Instant", "casting_cost": "10", "maintenance_cost": "-", "college": ["Clerical"], "prereqs": {"prereqs": [{"name": {"qualifier": "Power Investiture"}}]}}, "pDjFT4XSY-M8gezNu": {"name": "Divination: Cartomancy", "tags": ["Clerical"], "power_source": "Arcane", "spell_class": "Info", "casting_time": "1 hr", "duration": "Instant", "casting_cost": "10", "maintenance_cost": "-", "college": ["Clerical"], "prereqs": {"prereqs": [{"name": {"qualifier": "Power Investiture"}}]}}, "pvzC9uGJC2TI4bjVV": {"name": "Divination: Crystal-Gazing", "tags": ["Clerical"], "power_source": "Arcane", "spell_class": "Info", "casting_time": "1 hr", "duration": "Instant", "casting_cost": "10", "maintenance_cost": "-", "college": ["Clerical"], "prereqs": {"prereqs": [{"name": {"qualifier": "Power Investiture"}}]}}, "pLBdYCwGaHRK4049f": {"name": "Divination: Dactylomancy", "tags": ["Clerical"], "power_source": "Arcane", "spell_class": "Info", "casting_time": "1 hr", "duration": "Instant", "casting_cost": "10", "maintenance_cost": "-", "college": ["Clerical"], "prereqs": {"prereqs": [{"name": {"qualifier": "Power Investiture"}}]}}, "pDqU1Z6LeNZRagHbo": {"name": "Divination: Extispicy", "tags": ["Clerical"], "power_source": "Arcane", "spell_class": "Info", "casting_time": "1 hr", "duration": "Instant", "casting_cost": "10", "maintenance_cost": "-", "college": ["Clerical"], "prereqs": {"prereqs": [{"name": {"qualifier": "Power Investiture"}}]}}, "pV8LjpbX-zngsiASo": {"name": "Divination: Gastromancy", "tags": ["Clerical"], "power_source": "Arcane", "spell_class": "Info", "casting_time": "1 hr", "duration": "Instant", "casting_cost": "10", "maintenance_cost": "-", "college": ["Clerical"], "prereqs": {"prereqs": [{"name": {"qualifier": "Power Investiture"}}]}}, "pyxIAEn_3Q3WOt22I": {"name": "Divination: Geomancy", "tags": ["Clerical"], "power_source": "Arcane", "spell_class": "Info", "casting_time": "1 hr", "duration": "Instant", "casting_cost": "10", "maintenance_cost": "-", "college": ["Clerical"], "prereqs": {"prereqs": [{"name": {"qualifier": "Power Investiture"}}]}}, "p_RmyXM8j45y8S-V0": {"name": "Divination: Lecanomancy", "tags": ["Clerical"], "power_source": "Arcane", "spell_class": "Info", "casting_time": "1 hr", "duration": "Instant", "casting_cost": "10", "maintenance_cost": "-", "college": ["Clerical"], "prereqs": {"prereqs": [{"name": {"qualifier": "Power Investiture"}}]}}, "pz5CR0jGvmPOJxd7j": {"name": "Divination: Numerology", "tags": ["Clerical"], "power_source": "Arcane", "spell_class": "Info", "casting_time": "1 hr", "duration": "Instant", "casting_cost": "10", "maintenance_cost": "-", "college": ["Clerical"], "prereqs": {"prereqs": [{"name": {"qualifier": "Power Investiture"}}]}}, "pYvvis1silFfsHWpE": {"name": "Divination: Oneiromancy", "tags": ["Clerical"], "power_source": "Arcane", "spell_class": "Info", "casting_time": "1 hr", "duration": "Instant", "casting_cost": "10", "maintenance_cost": "-", "college": ["Clerical"], "prereqs": {"prereqs": [{"name": {"qualifier": "Power Investiture"}}]}}, "pojduC36ScgdfY4NX": {"name": "Divination: Physiognomy", "tags": ["Clerical"], "power_source": "Arcane", "spell_class": "Info", "casting_time": "1 hr", "duration": "Instant", "casting_cost": "10", "maintenance_cost": "-", "college": ["Clerical"], "prereqs": {"prereqs": [{"name": {"qualifier": "Power Investiture"}}]}}, "pLIP8lTYUzHjb0Xvo": {"name": "Divination: Pyromancy", "tags": ["Clerical"], "power_source": "Arcane", "spell_class": "Info", "casting_time": "1 hr", "duration": "Instant", "casting_cost": "10", "maintenance_cost": "-", "college": ["Clerical"], "prereqs": {"prereqs": [{"name": {"qualifier": "Power Investiture"}}]}}, "p2qnOdQRS6YrYmR61": {"name": "Divination: Sortilege", "tags": ["Clerical"], "power_source": "Arcane", "spell_class": "Info", "casting_time": "1 hr", "duration": "Instant", "casting_cost": "10", "maintenance_cost": "-", "college": ["Clerical"], "prereqs": {"prereqs": [{"name": {"qualifier": "Power Investiture"}}]}}, "p_6qHVu3eZynSepmg": {"name": "Divination: Symbol-Casting", "tags": ["Clerical"], "power_source": "Arcane", "spell_class": "Info", "casting_time": "1 hr", "duration": "Instant", "casting_cost": "10", "maintenance_cost": "-", "college": ["Clerical"], "prereqs": {"prereqs": [{"name": {"qualifier": "Power Investiture"}}]}}, "p05ctSNgnM-LOfkp4": {"name": "Essential Food", "tags": ["Clerical"], "power_source": "Arcane", "spell_class": "Regular", "casting_time": "30 sec", "duration": "Indefinite", "casting_cost": "3 or 5", "maintenance_cost": "-", "college": ["Clerical"], "prereqs": {"prereqs": [{"name": {"qualifier": "Power Investiture"}}]}}, "pT_3htqitbb1lZHby": {"name": "Instant Neutralize Poison", "tags": ["Clerical"], "power_source": "Arcane", "spell_class": "Regular", "casting_time": "1 sec", "duration": "Permanent", "casting_cost": "8", "maintenance_cost": "-", "college": ["Clerical"], "prereqs": {"prereqs": [{"name": {"qualifier": "Power Investiture"}}]}}, "p-d-jmBZE-hCZ6zIJ": {"name": "Instant Restoration", "tags": ["Clerical"], "power_source": "Arcane", "spell_class": "Regular", "casting_time": "1 sec", "duration": "Permanent", "casting_cost": "50", "maintenance_cost": "-", "college": ["Clerical"], "prereqs": {"prereqs": [{"name": {"qualifier": "Power Investiture"}}]}}, "pnYSVBMn7YZLogSLc": {"name": "Monk's Banquet", "tags": ["Clerical"], "power_source": "Arcane", "spell_class": "Regular", "casting_time": "1 sec", "duration": "24 hrs", "casting_cost": "6", "maintenance_cost": "-", "college": ["Clerical"], "prereqs": {"prereqs": [{"name": {"qualifier": "Power Investiture"}}]}}, "pdC2bCavu67Qklzev": {"name": "Regeneration", "tags": ["Clerical"], "power_source": "Arcane", "spell_class": "Regular", "casting_time": "1 min", "duration": "Permanent", "casting_cost": "20", "maintenance_cost": "-", "college": ["Clerical"], "prereqs": {"prereqs": [{"name": {"qualifier": "Power Investiture"}}]}}, "p8e7uH7Okn1LGuCNP": {"name": "Summon Spirit", "tags": ["Clerical"], "power_source": "Arcane", "spell_class": "Info", "casting_time": "5 min", "duration": "1 min", "casting_cost": "20", "maintenance_cost": "10", "college": ["Clerical"], "prereqs": {"prereqs": [{"name": {"qualifier": "Power Investiture"}}]}}, "pWTce05N_ZmDOjEA7": {"name": "Suspend Curse", "tags": ["Clerical"], "power_source": "Arcane", "spell_class": "Regular", "casting_time": "1 min", "duration": "10 min", "casting_cost": "10", "maintenance_cost": "10", "college": ["Clerical"], "prereqs": {"prereqs": [{"name": {"qualifier": "Power Investiture"}}]}}, "p1bB3l8B6IzahOuEZ": {"name": "Wisdom", "tags": ["Clerical"], "power_source": "Arcane", "spell_class": "Regular", "casting_time": "1 sec", "duration": "1 min", "casting_cost": "4/pt of IQ", "maintenance_cost": "Same", "college": ["Clerical"], "prereqs": {"prereqs": [{"name": {"qualifier": "Power Investiture"}}]}}, "pOucj46GK9t957KVb": {"name": "Watchdog", "tags": ["Clerical"], "power_source": "Arcane", "spell_class": "Area", "casting_time": "10 sec", "duration": "10 hrs", "casting_cost": "1", "maintenance_cost": "Same", "college": ["Clerical"], "prereqs": {"prereqs": [{"name": {"qualifier": "Power Investiture"}}]}}}}, "PIJcE9Lix4ILEIKIy": {"name": "Power Investiture", "tags": ["Clerical"], "notes": "5", "children": {"pkaGswh4od4oGDBo3": {"name": "Remove Curse", "tags": ["Clerical"], "power_source": "Arcane", "spell_class": "Regular", "casting_time": "1 hr", "duration": "Permanent", "casting_cost": "20", "maintenance_cost": "-", "college": ["Clerical"], "prereqs": {"prereqs": [{"name": {"qualifier": "Power Investiture"}}]}}, "POHXKep3ONSENlG6f": {"name": "And choose from:", "children": {"pbrfkBJ2DFxxPIy-m": {"name": "Entrap Spirit", "tags": ["Clerical"], "power_source": "Arcane", "spell_class": "Special", "casting_time": "1 sec", "duration": "5 min", "casting_cost": "Varies", "maintenance_cost": "Varies", "college": ["Clerical"], "prereqs": {"prereqs": [{"name": {"qualifier": "Power Investiture"}}]}}, "pt0enpLK6vydJHJv9": {"name": "Gift of Letters", "tags": ["Clerical"], "power_source": "Arcane", "spell_class": "Regular", "casting_time": "1 sec", "duration": "1 min", "casting_cost": "Varies", "maintenance_cost": "Half", "college": ["Clerical"], "prereqs": {"prereqs": [{"name": {"qualifier": "Power Investiture"}}]}}, "pIvQfTZNqrYtzuRlI": {"name": "Gift of Tongues", "tags": ["Clerical"], "power_source": "Arcane", "spell_class": "Regular", "casting_time": "1 sec", "duration": "1 min", "casting_cost": "Varies", "maintenance_cost": "Half", "college": ["Clerical"], "prereqs": {"prereqs": [{"name": {"qualifier": "Power Investiture"}}]}}, "pBujdCSPcQ8dTn-h6": {"name": "Instant Regeneration", "tags": ["Clerical"], "power_source": "Arcane", "spell_class": "Regular", "casting_time": "1 sec", "duration": "Permanent", "casting_cost": "80", "maintenance_cost": "-", "college": ["Clerical"], "prereqs": {"prereqs": [{"name": {"qualifier": "Power Investiture"}}]}}, "pt0p5vAptqUs1HTEZ": {"name": "Oath", "tags": ["Clerical"], "power_source": "Arcane", "spell_class": "Regular", "casting_time": "1 min", "duration": "Permanent", "casting_cost": "4", "maintenance_cost": "-", "college": ["Clerical"], "prereqs": {"prereqs": [{"name": {"qualifier": "Power Investiture"}}]}}, "pgwut6FBcgmEEsXHQ": {"name": "Pentagram", "tags": ["Clerical"], "power_source": "Arcane", "spell_class": "Special", "casting_time": "1 sec/sq foot", "duration": "Permanent", "casting_cost": "1/sq foot", "maintenance_cost": "-", "college": ["Clerical"], "prereqs": {"prereqs": [{"name": {"qualifier": "Power Investiture"}}]}}, "pOZFZqIUQXq588W_I": {"name": "Resist Pressure", "tags": ["Clerical"], "power_source": "Arcane", "spell_class": "Regular", "casting_time": "1 sec", "duration": "1 min", "casting_cost": "Varies", "maintenance_cost": "-", "college": ["Clerical"], "prereqs": {"prereqs": [{"name": {"qualifier": "Power Investiture"}}]}}, "pDiJrE2aVbtuodnCF": {"name": "Seeker", "tags": ["Clerical"], "power_source": "Arcane", "spell_class": "Info", "casting_time": "1 sec", "duration": "Instant", "casting_cost": "3", "maintenance_cost": "-", "college": ["Clerical"], "prereqs": {"prereqs": [{"name": {"qualifier": "Power Investiture"}}]}}, "pHBIDC12qF_QSfiki": {"name": "See Secrets", "tags": ["Clerical"], "power_source": "Arcane", "spell_class": "Regular", "casting_time": "5 sec", "duration": "1 min", "casting_cost": "5", "maintenance_cost": "2", "college": ["Clerical"], "prereqs": {"prereqs": [{"name": {"qualifier": "Power Investiture"}}]}}, "pLTVV4TjXl7qoOdZr": {"name": "Sunlight", "tags": ["Clerical"], "power_source": "Arcane", "spell_class": "Area", "casting_time": "1 sec", "duration": "1 min", "casting_cost": "2", "maintenance_cost": "Half", "college": ["Clerical"], "prereqs": {"prereqs": [{"name": {"qualifier": "Power Investiture"}}]}}, "ptgimKeJO7uF4p_LN": {"name": "Vigil", "tags": ["Clerical"], "power_source": "Arcane", "spell_class": "Regular", "casting_time": "1 sec", "duration": "1 night", "casting_cost": "8", "maintenance_cost": "-", "college": ["Clerical"], "prereqs": {"prereqs": [{"name": {"qualifier": "Power Investiture"}}]}}}}}}, "PqYpBSWoRkZwlQEXy": {"name": "Power Investiture", "notes": "6", "children": {"pRRCL5arrbMtCmlDA": {"name": "Bind Spirit (@Spirit@)", "tags": ["Necromancy"], "power_source": "Arcane", "spell_class": "Regular", "casting_time": "5 min", "duration": "Permanent", "casting_cost": "Varies", "maintenance_cost": "-", "college": ["Clerical"], "prereqs": {"prereqs": [{"name": {"qualifier": "Power Investiture"}}]}}, "pIsYlqbFBOzMTUFSf": {"name": "Curse", "tags": ["Clerical"], "power_source": "Arcane", "spell_class": "Regular", "casting_time": "2/4/6 sec", "duration": "Varies", "casting_cost": "3/10/20", "maintenance_cost": "-", "college": ["Clerical"], "prereqs": {"prereqs": [{"name": {"qualifier": "Power Investiture"}}]}}, "pBZMF8GBb-SYzlE3T": {"name": "Drain Mana", "tags": ["Meta"], "power_source": "Arcane", "spell_class": "Area", "casting_time": "1 hr", "duration": "Permanent", "casting_cost": "10", "maintenance_cost": "-", "college": ["Clerical"], "prereqs": {"prereqs": [{"name": {"qualifier": "Power Investiture"}}]}}, "pEh1BEJslMybIKLxQ": {"name": "Pain", "tags": ["Body Control"], "power_source": "Arcane", "spell_class": "Regular", "casting_time": "2 sec", "duration": "1 sec", "casting_cost": "2", "maintenance_cost": "-", "college": ["Clerical"], "prereqs": {"prereqs": [{"name": {"qualifier": "Power Investiture"}}]}}, "p-Bcau2UUse9NGnTP": {"name": "Planar Summons (Divine Servitor)", "tags": ["Gate"], "power_source": "Arcane", "spell_class": "Special", "casting_time": "5 min", "duration": "1 hr", "casting_cost": "20#", "maintenance_cost": "-", "college": ["Clerical"], "prereqs": {"prereqs": [{"name": {"qualifier": "Power Investiture"}}]}}, "pfHgvLzn0fYJaX_5G": {"name": "Resurrection", "tags": ["Healing", "Necromancy"], "power_source": "Arcane", "spell_class": "Regular", "casting_time": "2 Hours", "duration": "Permanent", "casting_cost": "300", "maintenance_cost": "-", "college": ["Clerical"], "prereqs": {"prereqs": [{"name": {"qualifier": "Power Investiture"}}]}}, "pv6TurEt0oCklQc16": {"name": "Sanctuary", "tags": ["Gate"], "power_source": "Arcane", "spell_class": "Special", "casting_time": "10 sec", "duration": "1 hr", "casting_cost": "5", "maintenance_cost": "Same", "college": ["Clerical"], "prereqs": {"prereqs": [{"name": {"qualifier": "Power Investiture"}}]}}, "p6FWghH4HWevwPy61": {"name": "Sunbolt", "tags": ["Clerical"], "power_source": "Arcane", "spell_class": "Missile", "casting_time": "1-3 sec", "duration": "Instant", "casting_cost": "1-3xMagery", "maintenance_cost": "-", "college": ["Clerical"], "weapons": {"WLUflOFum0YO6YYG0": {"defaults": [{}, {"name": "Innate Attack", "specialization": "Beam"}]}}, "prereqs": {"prereqs": [{"name": {"qualifier": "Power Investiture"}}]}}, "pcLq5FOKcksGCQkPL": {"name": "Suspend Mana", "tags": ["Clerical"], "power_source": "Arcane", "spell_class": "Area", "casting_time": "10 min", "duration": "Varies", "casting_cost": "5", "maintenance_cost": "-", "college": ["Clerical"], "prereqs": {"prereqs": [{"name": {"qualifier": "Power Investiture"}}]}}}}}}}}}}}}