{
    "traits": {
        "Thy-MMg1qTDxF2-5C": {
            "name": "",
            "children": {
                "T3njsKllreW4FKIJo": {
                    "name": "",
                    "children": {
                        "tEUxyzqMJ2KRvNZ6X": {
                            "name": "",
                            "tags": [
                                "",
                                ""
                            ],
                            "notes": "",
                            "weapons": {
                                "wjWB248DBgOn2M2oE": {
                                    "usage": "",
                                    "defaults": [
                                        {},
                                        {
                                            "name": ""
                                        },
                                        {
                                            "name": ""
                                        },
                                        {
                                            "name": ""
                                        }
                                    ]
                                }
                            }
                        },
                        "t9TdCYz-DeqQ8hEeX": {
                            "name": "",
                            "tags": [
                                "",
                                "",
                                ""
                            ],
                            "modifiers": {
                                "mTlsUGAyOpFVudNup": {
                                    "name": ""
                                },
                                "mf46QvwSkCn7Ysvks": {
                                    "name": "",
                                    "notes": ""
                                },
                                "milNLqj_pjoKNK0bu": {
                                    "name": "",
                                    "notes": ""
                                },
                                "mvzL_NageWS1uGHRg": {
                                    "name": "",
                                    "notes": ""
                                },
                                "mX7-iAmKeWuOLHKB2": {
                                    "name": ""
                                },
                                "mkkWp1XyEzizs6Acs": {
                                    "name": "",
                                    "notes": ""
                                },
                                "m0dm3xoe-Yy-hrDMk": {
                                    "name": "",
                                    "notes": ""
                                },
                                "mNYgmwf56-ZPGZfz8": {
                                    "name": ""
                                },
                                "mTrS22UilOw89NXuM": {
                                    "name": ""
                                },
                                "m13qMHQkPGRKEBbMp": {
                                    "name": "",
                                    "notes": ""
                                },
                                "mIxE_Jvv4tovT6qIZ": {
                                    "name": "",
                                    "notes": ""
                                },
                                "moS2uLi_5SGcloobG": {
                                    "name": "",
                                    "notes": ""
                                },
                                "mP81RhOz0JBt0wOEU": {
                                    "name": "",
                                    "notes": ""
                                },
                                "mVF7d4gqaDp1n_lmu": {
                                    "name": ""
                                },
                                "mrBGSGDi2rc2Wrcho": {
                                    "name": ""
                                },
                                "m9Uj83jaHT9L24YCg": {
                                    "name": ""
                                },
                                "mXbQ9JXvDXH-uvWN0": {
                                    "name": ""
                                }
                            }
                        },
                        "t7seNq0ozvfj_K_w5": {
                            "name": "",
                            "tags": [
                                "",
                                "",
                                ""
                            ]
                        },
                        "tN2B6Nvs5JDOayttz": {
                            "name": "",
                            "tags": [
                                "",
                                "",
                                ""
                            ],
                            "weapons": {
                                "wXmBBwANWLF1n_jqB": {
                                    "usage": "",
                                    "defaults": [
                                        {
                                            "name": ""
                                        }
                                    ]
                                }
                            }
                        }
                    }
                },
                "Tt0feyvfwo-CkLlaQ": {
                    "name": "",
                    "children": {
                        "t4zRJcR1PM7z1I6GM": {
                            "name": "",
                            "tags": [
                                "",
                                "",
                                ""
                            ],
                            "modifiers": {
                                "moo7-NdZR__WNjGp_": {
                                    "name": ""
                                }
                            }
                        },
                        "tW7WeEMDjTc-jcvP7": {
                            "name": "",
                            "tags": [
                                "",
                                "",
                                ""
                            ]
                        },
                        "tWGQM1HQhRlAnE7wP": {
                            "name": "",
                            "tags": [
                                "",
                                "",
                                ""
                            ],
                            "modifiers": {
                                "mi4ZdISDw3P94Z5FV": {
                                    "name": ""
                                },
                                "mC5p4hx1kG1VPaFK1": {
                                    "name": ""
                                },
                                "mbvogKKcdKeudQK6h": {
                                    "name": ""
                                }
                            }
                        }
                    }
                },
                "TzvyT4SEV0lQHo1WJ": {
                    "name": "",
                    "children": {
                        "tubrbkTPk7eN4KeZL": {
                            "name": "",
                            "tags": [
                                "",
                                ""
                            ],
                            "prereqs": {
                                "prereqs": [
                                    {
                                        "name": {
                                            "qualifier": ""
                                        }
                                    }
                                ]
                            }
                        },
                        "ts1JW4Q4aZbMf2mOy": {
                            "name": "",
                            "tags": [
                                "",
                                ""
                            ],
                            "prereqs": {
                                "prereqs": [
                                    {
                                        "name": {
                                            "qualifier": ""
                                        }
                                    }
                                ]
                            }
                        },
                        "tmDAtf5Y1Ml47Jz8m": {
                            "name": "",
                            "tags": [
                                "",
                                ""
                            ],
                            "notes": "",
                            "features": [
                                {
                                    "name": {
                                        "qualifier": ""
                                    }
                                },
                                {
                                    "name": {
                                        "qualifier": ""
                                    }
                                },
                                {
                                    "name": {
                                        "qualifier": ""
                                    }
                                },
                                {
                                    "name": {
                                        "qualifier": ""
                                    }
                                },
                                {
                                    "name": {
                                        "qualifier": ""
                                    }
                                },
                                {
                                    "name": {
                                        "qualifier": ""
                                    }
                                },
                                {
                                    "name": {
                                        "qualifier": ""
                                    }
                                },
                                {
                                    "name": {
                                        "qualifier": ""
                                    }
                                },
                                {
                                    "name": {
                                        "qualifier": ""
                                    }
                                },
                                {
                                    "name": {
                                        "qualifier": ""
                                    }
                                },
                                {
                                    "name": {
                                        "qualifier": ""
                                    }
                                },
                                {
                                    "name": {
                                        "qualifier": ""
                                    }
                                }
                            ],
                            "prereqs": {
                                "prereqs": [
                                    {
                                        "name": {
                                            "qualifier": ""
                                        }
                                    }
                                ]
                            }
                        },
                        "trONu6NZD-wdu4Vtp": {
                            "name": "",
                            "tags": [
                                "",
                                "",
                                ""
                            ]
                        }
                    }
                }
            }
        }
    }
}
