{
    "traits": {
        "TJICS8BmQe6hVcmFE": {
            "name": "",
            "children": {
                "tNuiwuSvd_WtVfGxU": {
                    "name": "",
                    "tags": [
                        "",
                        "",
                        ""
                    ],
                    "modifiers": {
                        "mpgQvJSi8WFT2L-Qe": {
                            "name": ""
                        },
                        "mJVR6dQHmkKcqGOTO": {
                            "name": "",
                            "features": [
                                {
                                    "name": {
                                        "qualifier": ""
                                    }
                                },
                                {
                                    "name": {
                                        "qualifier": ""
                                    }
                                },
                                {
                                    "name": {
                                        "qualifier": ""
                                    }
                                },
                                {
                                    "name": {
                                        "qualifier": ""
                                    },
                                    "specialization": {
                                        "qualifier": ""
                                    }
                                },
                                {
                                    "name": {
                                        "qualifier": ""
                                    },
                                    "specialization": {
                                        "qualifier": ""
                                    }
                                }
                            ]
                        }
                    },
                    "features": [
                        {
                            "name": {
                                "qualifier": ""
                            }
                        },
                        {
                            "name": {
                                "qualifier": ""
                            },
                            "specialization": {
                                "qualifier": ""
                            }
                        },
                        {
                            "name": {
                                "qualifier": ""
                            },
                            "specialization": {
                                "qualifier": ""
                            }
                        },
                        {
                            "name": {
                                "qualifier": ""
                            },
                            "specialization": {
                                "qualifier": ""
                            }
                        }
                    ]
                },
                "t7CKLcmwxqR6Q15Cf": {
                    "name": "",
                    "tags": [
                        "",
                        ""
                    ],
                    "notes": "",
                    "features": [
                        {
                            "name": {
                                "qualifier": ""
                            }
                        }
                    ],
                    "prereqs": {
                        "prereqs": [
                            {
                                "name": {
                                    "qualifier": ""
                                }
                            }
                        ]
                    }
                },
                "tmejIjKJOG39uIfxt": {
                    "name": "",
                    "tags": [
                        "",
                        ""
                    ],
                    "modifiers": {
                        "mIdeD6hDElswVjHvI": {
                            "name": ""
                        },
                        "mquERXtCZqFPLoT_I": {
                            "name": ""
                        },
                        "mOk3TzZ3eLBU8pP2A": {
                            "name": ""
                        },
                        "m4pQ62sPFKIN1Ybb6": {
                            "name": ""
                        },
                        "mz0K3lOLQHBAfnYzt": {
                            "name": ""
                        },
                        "m04ge17at1OFR9AIo": {
                            "name": ""
                        },
                        "mH-j5teJXrsYrqDnm": {
                            "name": ""
                        },
                        "mKmn6Hf8GrndoHKez": {
                            "name": ""
                        },
                        "mepIJ4o2bU-OTuROf": {
                            "name": ""
                        },
                        "mN-yfoHhbCXVA1Qfk": {
                            "name": "",
                            "notes": ""
                        },
                        "m8RlgTg1lRDs4KnYD": {
                            "name": "",
                            "notes": ""
                        },
                        "m-FH1jVcE1Ta3T6wE": {
                            "name": "",
                            "notes": ""
                        },
                        "mV7E-ectjzHOnrBIl": {
                            "name": "",
                            "notes": ""
                        },
                        "mFe_tD7x3FRbgSQZk": {
                            "name": "",
                            "notes": ""
                        },
                        "mwHq26QIFfWzmi1wi": {
                            "name": "",
                            "notes": ""
                        },
                        "mRElrBroOTr6LNxB4": {
                            "name": ""
                        },
                        "mZzE6rNZw1wZhnQ1v": {
                            "name": "",
                            "notes": ""
                        },
                        "mf9qLAQZS4ao_ctfm": {
                            "name": "",
                            "notes": ""
                        },
                        "mQF9F_-Qh21J-cGQZ": {
                            "name": ""
                        },
                        "m9MD1qXSLEaWuy9GR": {
                            "name": ""
                        },
                        "mcmATpc5u0vrmWubl": {
                            "name": ""
                        },
                        "mIWJimcnKeJJiJRoF": {
                            "name": ""
                        }
                    }
                }
            }
        },
        "Tkp4CEwhOgstjUrpL": {
            "name": "",
            "children": {
                "Tf-5pVnwKeYt0vLNR": {
                    "name": "",
                    "children": {
                        "tP-eAohzEwjgqfH7J": {
                            "name": "",
                            "tags": [
                                "",
                                ""
                            ]
                        },
                        "tFvuo2Y1v6QpgbQq0": {
                            "name": "",
                            "tags": [
                                "",
                                ""
                            ]
                        },
                        "thEBJJgh9ck0EVBSJ": {
                            "name": "",
                            "tags": [
                                "",
                                ""
                            ],
                            "modifiers": {
                                "mypi1GauDhmX19psv": {
                                    "name": "",
                                    "notes": ""
                                },
                                "mrnVMxox_NWcs_E0L": {
                                    "name": "",
                                    "notes": ""
                                },
                                "mW4ZVip-F3ejRNXQs": {
                                    "name": "",
                                    "notes": ""
                                },
                                "mJKd4vAZfFWW2OffG": {
                                    "name": ""
                                },
                                "mfqtiebyoYb3P2sCU": {
                                    "name": ""
                                },
                                "m1ZmNhoOUvw_i1ELP": {
                                    "name": "",
                                    "notes": ""
                                },
                                "mLarMQmBWCqE46eM7": {
                                    "name": "",
                                    "notes": ""
                                },
                                "m7bO_o0i7UQMiJyLq": {
                                    "name": "",
                                    "notes": ""
                                },
                                "m3-LUdjc6zKj2apFR": {
                                    "name": "",
                                    "notes": ""
                                },
                                "mVDynBmAuEec4-Qu5": {
                                    "name": ""
                                },
                                "mhttdIs9yRsSoQSiM": {
                                    "name": ""
                                },
                                "mrQSfbcUpEImSWAlr": {
                                    "name": ""
                                },
                                "mRsqgSUn9mthPNkR0": {
                                    "name": ""
                                },
                                "m34c2sivG_8_kwPtR": {
                                    "name": "",
                                    "notes": ""
                                },
                                "mptDvMo8e_KyxBgeN": {
                                    "name": "",
                                    "notes": ""
                                },
                                "m03RG94mqsqtsKLH7": {
                                    "name": ""
                                },
                                "mLvk2gWep3IXmp7hm": {
                                    "name": ""
                                },
                                "me8u7GXnEmYkXd1mC": {
                                    "name": ""
                                }
                            }
                        },
                        "tUH7hwop_pFnqSsaG": {
                            "name": "",
                            "tags": [
                                "",
                                ""
                            ]
                        },
                        "tApe8YpNFw8yGLEGT": {
                            "name": "",
                            "tags": [
                                "",
                                ""
                            ],
                            "modifiers": {
                                "mx2J0HFDvrZkdnpbO": {
                                    "name": ""
                                },
                                "mfcJWm6bTxmmOF022": {
                                    "name": ""
                                },
                                "m7b4RoFMKcnRbyYku": {
                                    "name": ""
                                },
                                "mrXIoQrEdLAMszqoq": {
                                    "name": ""
                                },
                                "muy2Tz0AP0NhSWCh5": {
                                    "name": ""
                                },
                                "mzcAG_zuBY46C73jD": {
                                    "name": ""
                                }
                            }
                        }
                    }
                },
                "tKY7f-jakdSTHjFIk": {
                    "name": "",
                    "tags": [
                        ""
                    ],
                    "notes": ""
                }
            }
        }
    },
    "skills": {
        "SLrp6X3apK2L1wJm0": {
            "name": "",
            "children": {
                "s4ZxlkHdDdVLk3SYD": {
                    "name": "",
                    "tags": [
                        ""
                    ],
                    "specialization": "",
                    "defaults": [
                        {},
                        {},
                        {
                            "name": "",
                            "specialization": ""
                        },
                        {
                            "name": ""
                        }
                    ]
                },
                "sBgsmhKg4A6vbEnvk": {
                    "name": "",
                    "tags": [
                        ""
                    ],
                    "specialization": "",
                    "defaults": [
                        {},
                        {},
                        {
                            "name": ""
                        }
                    ]
                }
            }
        },
        "smtFu2R7Zh_crvhdG": {
            "name": "",
            "tags": [
                "",
                ""
            ],
            "specialization": "",
            "defaults": [
                {},
                {
                    "name": "",
                    "specialization": ""
                },
                {
                    "name": ""
                },
                {
                    "name": ""
                }
            ]
        },
        "S8plbYXGnkPkvSyz8": {
            "name": "",
            "children": {
                "sh1kZrwKSS5yl3JuG": {
                    "name": "",
                    "tags": [
                        "",
                        "",
                        "",
                        "",
                        ""
                    ]
                },
                "sJPC7mlAH9qCPhCbH": {
                    "name": "",
                    "tags": [
                        "",
                        "",
                        ""
                    ]
                },
                "s8tWlCCLfRvQV2tPS": {
                    "name": "",
                    "tags": [
                        "",
                        ""
                    ]
                },
                "sbuX-MuYP8tkv2PUc": {
                    "name": "",
                    "tags": [
                        ""
                    ],
                    "specialization": "",
                    "defaults": [
                        {},
                        {
                            "name": ""
                        },
                        {
                            "name": "",
                            "specialization": ""
                        },
                        {
                            "name": "",
                            "specialization": ""
                        }
                    ]
                },
                "sJ4pWAW6BZqPJv8WW": {
                    "name": "",
                    "tags": [
                        ""
                    ],
                    "specialization": "",
                    "defaults": [
                        {},
                        {
                            "name": "",
                            "specialization": ""
                        },
                        {
                            "name": "",
                            "specialization": ""
                        },
                        {
                            "name": ""
                        }
                    ]
                },
                "sC-PDNwcBYAYYaY3c": {
                    "name": "",
                    "tags": [
                        "",
                        "",
                        ""
                    ],
                    "specialization": ""
                },
                "sJCes-NJxc4rAFnbU": {
                    "name": "",
                    "tags": [
                        "",
                        "",
                        ""
                    ],
                    "specialization": "",
                    "defaults": [
                        {},
                        {
                            "name": ""
                        }
                    ]
                },
                "s2ow4_KldmLhIpSYO": {
                    "name": "",
                    "tags": [
                        "",
                        "",
                        ""
                    ],
                    "specialization": "",
                    "defaults": [
                        {},
                        {
                            "name": ""
                        }
                    ]
                },
                "s1_9FD1cxop3LtsFZ": {
                    "name": "",
                    "tags": [
                        "",
                        "",
                        ""
                    ],
                    "specialization": "",
                    "defaults": [
                        {},
                        {
                            "name": ""
                        }
                    ]
                },
                "sAWggTDTkG8y_PDh8": {
                    "name": "",
                    "tags": [
                        "",
                        "",
                        ""
                    ],
                    "specialization": "",
                    "defaults": [
                        {},
                        {
                            "name": "",
                            "specialization": ""
                        },
                        {
                            "name": "",
                            "specialization": ""
                        },
                        {
                            "name": "",
                            "specialization": ""
                        },
                        {
                            "name": "",
                            "specialization": ""
                        },
                        {
                            "name": "",
                            "specialization": ""
                        },
                        {
                            "name": "",
                            "specialization": ""
                        },
                        {
                            "name": "",
                            "specialization": ""
                        },
                        {
                            "name": "",
                            "specialization": ""
                        }
                    ]
                },
                "s2GFwFSmDi-7vtTgV": {
                    "name": "",
                    "tags": [
                        "",
                        "",
                        ""
                    ],
                    "specialization": "",
                    "defaults": [
                        {},
                        {
                            "name": "",
                            "specialization": ""
                        },
                        {
                            "name": "",
                            "specialization": ""
                        },
                        {
                            "name": "",
                            "specialization": ""
                        },
                        {
                            "name": "",
                            "specialization": ""
                        },
                        {
                            "name": "",
                            "specialization": ""
                        },
                        {
                            "name": "",
                            "specialization": ""
                        },
                        {
                            "name": "",
                            "specialization": ""
                        },
                        {
                            "name": "",
                            "specialization": ""
                        },
                        {
                            "name": "",
                            "specialization": ""
                        }
                    ]
                },
                "swuTV_0ubeC1ymH_O": {
                    "name": "",
                    "tags": [
                        "",
                        "",
                        ""
                    ],
                    "specialization": "",
                    "defaults": [
                        {},
                        {
                            "name": "",
                            "specialization": ""
                        },
                        {
                            "name": "",
                            "specialization": ""
                        },
                        {
                            "name": "",
                            "specialization": ""
                        },
                        {
                            "name": "",
                            "specialization": ""
                        },
                        {
                            "name": "",
                            "specialization": ""
                        },
                        {
                            "name": "",
                            "specialization": ""
                        },
                        {
                            "name": "",
                            "specialization": ""
                        },
                        {
                            "name": "",
                            "specialization": ""
                        },
                        {
                            "name": "",
                            "specialization": ""
                        }
                    ]
                },
                "szDXvHJyWR0_wQG9R": {
                    "name": "",
                    "tags": [
                        "",
                        "",
                        ""
                    ],
                    "specialization": "",
                    "defaults": [
                        {},
                        {
                            "name": "",
                            "specialization": ""
                        },
                        {
                            "name": "",
                            "specialization": ""
                        },
                        {
                            "name": "",
                            "specialization": ""
                        },
                        {
                            "name": "",
                            "specialization": ""
                        },
                        {
                            "name": "",
                            "specialization": ""
                        },
                        {
                            "name": "",
                            "specialization": ""
                        },
                        {
                            "name": "",
                            "specialization": ""
                        },
                        {
                            "name": "",
                            "specialization": ""
                        }
                    ]
                },
                "sfSSajNZw1nVNvPk4": {
                    "name": "",
                    "tags": [
                        "",
                        "",
                        ""
                    ],
                    "specialization": "",
                    "defaults": [
                        {},
                        {
                            "name": "",
                            "specialization": ""
                        },
                        {
                            "name": "",
                            "specialization": ""
                        },
                        {
                            "name": "",
                            "specialization": ""
                        },
                        {
                            "name": "",
                            "specialization": ""
                        },
                        {
                            "name": "",
                            "specialization": ""
                        },
                        {
                            "name": "",
                            "specialization": ""
                        },
                        {
                            "name": "",
                            "specialization": ""
                        },
                        {
                            "name": "",
                            "specialization": ""
                        }
                    ]
                },
                "sNRYWPLYkX1w41yLF": {
                    "name": "",
                    "tags": [
                        ""
                    ]
                },
                "sJ5LAEHuD8OGhOAZN": {
                    "name": "",
                    "tags": [
                        "",
                        "",
                        ""
                    ],
                    "defaults": [
                        {
                            "name": ""
                        },
                        {
                            "name": ""
                        },
                        {
                            "name": ""
                        }
                    ]
                },
                "sTiYTYV9hgmI3WSTT": {
                    "name": "",
                    "tags": [
                        "",
                        "",
                        ""
                    ]
                },
                "s4PDPZaGXOS2DkNIn": {
                    "name": "",
                    "tags": [
                        ""
                    ]
                },
                "sVftv5XGWNIdIKL_L": {
                    "name": "",
                    "tags": [
                        "",
                        "",
                        "",
                        ""
                    ],
                    "specialization": "",
                    "defaults": [
                        {},
                        {
                            "name": ""
                        },
                        {
                            "name": "",
                            "specialization": ""
                        },
                        {
                            "name": "",
                            "specialization": ""
                        },
                        {
                            "name": "",
                            "specialization": ""
                        }
                    ]
                },
                "sxkB6zeAHzIyLWA7X": {
                    "name": "",
                    "tags": [
                        ""
                    ],
                    "defaults": [
                        {},
                        {
                            "name": "",
                            "specialization": ""
                        }
                    ]
                },
                "sQe3pFhMg4WWGwGsz": {
                    "name": "",
                    "tags": [
                        "",
                        "",
                        "",
                        ""
                    ]
                }
            }
        }
    }
}
