{"traits": {"TJoT5kTYgyUEyI5XV": {"name": "Bush Robot", "tags": ["Race", "Robot"], "children": {"TaRkuBCpUz34inLxI": {"name": "Advantages", "children": {"t85LPQ9go7KIaKLwm": {"name": "360\u00b0 Vision", "tags": ["Advantage", "Exotic", "Physical"], "modifiers": {"mj4XIdFInWv0zllI2": {"name": "Easy to hit "}, "mhXit_HucAFb_kcgd": {"name": "Panoptic 1"}, "mIJFBDGcy5kUzBu0k": {"name": "Panoptic 2"}}}, "tmaCAtyXO0tJvCx4K": {"name": "Absolute Direction", "tags": ["Advantage", "Mental", "Physical"], "modifiers": {"m9NyXl43LoyqNxMRR": {"name": "Requires signal"}, "mEsOmeuuPKh4IWLKg": {"name": "3D Spatial Sense", "features": [{"name": {"qualifier": "piloting"}}, {"name": {"qualifier": "aerobatics"}}, {"name": {"qualifier": "free fall"}}, {"name": {"qualifier": "navigation"}, "specialization": {"qualifier": "hyperspace"}}, {"name": {"qualifier": "navigation"}, "specialization": {"qualifier": "space"}}]}}, "features": [{"name": {"qualifier": "body sense"}}, {"name": {"qualifier": "navigation"}, "specialization": {"qualifier": "air"}}, {"name": {"qualifier": "navigation"}, "specialization": {"qualifier": "land"}}, {"name": {"qualifier": "navigation"}, "specialization": {"qualifier": "sea"}}]}, "tI0M3UFhRoVPgpGIB": {"name": "Ambidexterity", "tags": ["Advantage", "Physical"]}, "tEosOhKnIBTePCSNl": {"name": "Damage Resistance", "tags": ["Advantage", "Exotic", "Physical"], "modifiers": {"mzJo2KncaWpXxS_e4": {"name": "Ablative"}, "mzeWDrgEVxN_P235J": {"name": "Absorption"}, "mj5g34KPTt5ZbbY3u": {"name": "Absorption"}, "mI0RO2Oz7PAEYc5pw": {"name": "Absorption"}, "mz0dsNaP6SZfwfPX1": {"name": "Can't wear armor"}, "m-PCN37AoedqWS0aN": {"name": "Directional"}, "mYrfwBz_kRZsGGiE0": {"name": "Directional"}, "m-qXmVOXtFhRJbVLD": {"name": "Flexible"}, "mwNlVssp7XFEJf-DN": {"name": "Hardened"}, "mnAm5-Qag_XbTs5vc": {"name": "Limited"}, "m6n8l2cszpsvP39PB": {"name": "Limited"}, "msdqNU8VcEQRporKT": {"name": "Limited"}, "m_Csdl3oW8MYJCCGx": {"name": "Limited"}, "mljTfEKBRv9B_-1mN": {"name": "Reflection"}, "mPUa9TbqOcAcMtB-A": {"name": "Semi-Ablative"}, "m2K9tHJamY7iZ6zjc": {"name": "Tough Skin"}}, "features": [{}, {}, {}, {}, {}, {}, {}, {}, {}, {}, {}, {}, {}, {}]}, "tqQG6TEhyIYwGe8_o": {"name": "Discriminatory Taste", "tags": ["Advantage", "Exotic", "Physical"], "modifiers": {"msTtqrMlEql-ntboV": {"name": "Profiling"}}}, "tKx1Qvl5PDWJ7ITIC": {"name": "Doesn't Breathe", "tags": ["Advantage", "Exotic", "Physical"], "modifiers": {"mO1vqk4NXpN4WKm3x": {"name": "Gills"}, "mUph5UmYhJmZAxkE8": {"name": "Gills"}, "mFxmWE6xMO3lZXhjt": {"name": "Oxygen Absorption"}, "mcLWJP_BBb8EuSucH": {"name": "Oxygen Storage"}, "myT7cKCPptSpbuqIx": {"name": "Oxygen Storage"}, "m9UqhdEdzvMgDRMDG": {"name": "Oxygen Storage"}, "mFEjiTLm6tuQJKna1": {"name": "Oxygen Storage"}, "mQ4DS-JuRoZgoOOpY": {"name": "Oxygen Storage"}, "mYmhspUG8hsIkkHsH": {"name": "Oxygen Combustion"}}}, "tx6x-ABlyPpXDPBIK": {"name": "Enhanced Tracking", "tags": ["Advantage", "Exotic", "Physical"], "modifiers": {"mLHMKPvS6DQB3dSC6": {"name": "Multiple Lock-Ons"}}}, "tflnO4Zy2pzBAgpT7": {"name": "Extra Arm", "tags": ["Advantage", "Exotic", "Physical"], "modifiers": {"mFNYnSA3YiNTTK6Uv": {"name": "Extra-Flexible"}, "mDyOFWuyFYJRugKvU": {"name": "Long"}, "m5moCKRR_6FVBQM2i": {"name": "Foot Manipulators"}, "mc_tzeeWZcwwQVpQ3": {"name": "No Physical Attack"}, "mCQJzuNQEY--eYkgH": {"name": "Short"}, "mWZ5sg0l_StySEHBW": {"name": "Weak"}, "mgJaWwu4CEcjiFh_m": {"name": "Weak"}, "mPzvrXvBqNe-j02lR": {"name": "Weapon Mount"}}}, "taVuXKNYSsUbrFlcq": {"name": "Extra Attack", "tags": ["Advantage", "Physical"], "modifiers": {"m9VuTdoZp2MgCIdg3": {"name": "Multi-Strike"}, "mLw8hiXm1k1_lHGm_": {"name": "Single Skill"}}}, "tYgdp99sNyhDq1sKQ": {"name": "Flexibility (Double-Jointed)", "tags": ["Advantage", "Physical"], "features": [{"name": {"qualifier": "climbing"}}, {"name": {"qualifier": "escape"}}, {"name": {"qualifier": "erotic art"}}]}, "tZM6gHBXnwArEIrk2": {"name": "Gadgeteer", "tags": ["Advantage", "Mental"], "modifiers": {"mMlRH1_ZmT0KtfD_G": {"name": "Quick"}, "mRqvSKQhv5LZ6noaA": {"name": "Not for inventing new gadgets"}}}, "tU-yCSVj3yzep__ON": {"name": "High Manual Dexterity", "tags": ["Advantage", "Physical"], "features": [{"name": {"qualifier": "artist"}}, {"name": {"qualifier": "jeweler"}}, {"name": {"qualifier": "knot-tying"}}, {"name": {"qualifier": "leatherworking"}}, {"name": {"qualifier": "lockpicking"}}, {"name": {"qualifier": "pickpocket"}}, {"name": {"qualifier": "sewing"}}, {"name": {"qualifier": "sleight of hand"}}, {"name": {"qualifier": "surgery"}}, {"name": {"qualifier": "machinist"}}, {"name": {"qualifier": "mechanic"}}]}, "tbQFkVi_uPh5O84BO": {"name": "Hyperspectral Vision", "tags": ["Advantage", "Exotic", "Physical"], "modifiers": {"m_pN5vazOKmm4-bw8": {"name": "Extended Low-Band"}, "m2uQKLVxId4gR74Fh": {"name": "Extended High-Band"}, "mdk2-ciuYNoMpV4kK": {"name": "Extended"}}, "prereqs": {"prereqs": [{"name": {"qualifier": "infravision"}}, {"name": {"qualifier": "ultravision"}}]}}, "t5Gqaz2QxgGFAuhsH": {"name": "Injury Tolerance (No Brain)", "tags": ["Advantage", "Exotic", "Physical"]}, "t-b0LpOYDTTNVs2s1": {"name": "Injury Tolerance (No Eyes)", "tags": ["Advantage", "Exotic", "Physical"]}, "TpZ0yUfdtrXKheiPO": {"name": "Meta-Trait: Machine", "children": {"tv8lAPfkSmoO5Ca_R": {"name": "Eight-hour energy reserve, Refuel 3 times per day", "tags": ["Physical"]}, "tHxHhO9qN_49P90iB": {"name": "Injury Tolerance (No Blood)", "tags": ["Exotic", "Physical"]}, "ttNAmC18dUC3C3FqP": {"name": "Injury Tolerance (Unliving)", "tags": ["Exotic", "Physical"]}, "tFBeBV8hRJ5kz8iuR": {"name": "No fatigue points, Don't spend fatigue points", "tags": ["Physical"]}, "tFRHAR5hczOj36Deo": {"name": "Resistant (Immunity to Metabolic Hazards)", "tags": ["Physical"]}, "tUfUa5dCxp4oe1wIN": {"name": "Unhealing (Total)", "tags": ["Exotic", "Physical"]}, "tgcZU2NMNFjRavlqd": {"name": "Wears out instead of aging", "tags": ["Physical"]}}}, "tE_O2ctPikCXtHe0R": {"name": "Microscopic Vision", "tags": ["Advantage", "Exotic", "Physical"]}, "ttlRUFza_MbnBmm-V": {"name": "Protected Sense (Vision)", "tags": ["Advantage", "Exotic", "Physical"]}, "tHDPciAvPP4Rh8ZXP": {"name": "Scanning Sense", "tags": ["Advantage", "Exotic", "Physical"], "modifiers": {"maE5LmWA-KiNN23JS": {"name": "Imaging Radar"}, "mQPIkgQMov9Qa5Un8": {"name": "Radar"}, "m-YW4vGywmvQvEhMK": {"name": "Ladar"}, "myMOgqSVIQiD9_d4Q": {"name": "Para-Radar"}, "mLxUpRC3Ur7kK_7uW": {"name": "Sonar"}, "mik2poouMz3gx_se6": {"name": "Extended Arc"}, "mNjyC4TDeBuVDHcmz": {"name": "Extended Arc"}, "mgmin3F9Swv_LYqvR": {"name": "Low-Probability Intercept"}, "mKRgwV-QrGLEnNKns": {"name": "Multi-Mode"}, "maLZ9vbnomZte4QC7": {"name": "Penetrating"}, "m8KqrIOfsQjSHpo5-": {"name": "Targeting"}, "mBXhybxepLcsGahra": {"name": "Targeting Only"}, "m1qsdBF8RfmNtpTR5": {"name": "Active IR"}, "mHRKojG24VeJKcq_z": {"name": "T-Ray Vision"}, "mh3oXIa8yGP8v-vac": {"name": "Bio-Scan"}, "mdjwiAsuDxvTWKZvn": {"name": "No Intercept"}, "mhQvD-QdFHzECTA52": {"name": "Scanner"}, "mLPp5Eq1qZzb8n6KM": {"name": "Field Sense"}}}, "tp9gDc6PpyTyQ6Ieo": {"name": "Sealed", "tags": ["Advantage", "Exotic", "Physical"]}, "tYXdtVt4Db_ulR-yG": {"name": "Sensitive Touch", "tags": ["Advantage", "Exotic", "Physical"], "modifiers": {"mThFKVTWAjz0kYqKw": {"name": "Stethoscopic"}, "mrYEqwp5se2E2GLMk": {"name": "Ultra-Fine"}}}, "tyqDAeFCXicXsIZ6G": {"name": "Telecommunication", "tags": ["Advantage", "Exotic", "Mental", "Physical"], "modifiers": {"m18sCyAT9IKnYIGCr": {"name": "Broadcast"}, "mu--4sirQ4OX9L0pW": {"name": "Burst"}, "mm6MRTzfDCsmaCagr": {"name": "Directional Sound"}, "mY0r0XylVl1cwjq8j": {"name": "FTL"}, "mKVGhsT0RVje1D5Fi": {"name": "Gravity Ripple"}, "mMAlKS8SXRxHPF9qe": {"name": "Infrared Communication"}, "mazgqNpyCm_ZZDoJj": {"name": "Laser Communication"}, "mxP52GAjPAtpi5GJG": {"name": "Neutrino"}, "mYXAvvbjW6zNMYojP": {"name": "Racial"}, "mv59qb1diwmfVOlPg": {"name": "Radio"}, "mmr8cloaTQC3AA-PA": {"name": "Receive Only"}, "mN1oNoSMYbpUJEYLX": {"name": "Secure"}, "mFwnLGfRUpy-dtfbC": {"name": "Send Only"}, "myBTUE8DoAgkLCLO5": {"name": "Sensie"}, "mib8BCMMkdATzDd7g": {"name": "Short Wave"}, "m1rrCcoAanHxLqLnd": {"name": "Sonar"}, "mIC99as-i1dM8o7m2": {"name": "Telesend"}, "mxICkDytEYLwL1YBK": {"name": "Universal"}, "mrFUV7SCViZkX4Twa": {"name": "Vague"}, "mgWe-XVZYjmfEGaBu": {"name": "Video"}}}, "typ7jlBsCoLX_sbd8": {"name": "Telecommunication", "tags": ["Advantage", "Exotic", "Mental", "Physical"], "modifiers": {"mSrKVlMxAe4yft8T6": {"name": "Infrared Communication"}, "mtrGvXT6McOE7tuLj": {"name": "Laser Communication"}, "mv_NwOrjzzLquEYsP": {"name": "Radio"}, "mZPzko1OQb_gnHDBr": {"name": "Telesend"}, "mhGd-Oj6RvODGU9gZ": {"name": "Broadcast"}, "m4vNEKO1VfIBsR305": {"name": "Short Wave"}, "m1BVyNZWpLjogmdpF": {"name": "Universal"}, "m8IN0SvwAxZT9YSBB": {"name": "Video"}, "mFO_pbnH40z5a-a2q": {"name": "Racial"}, "mzMVvdyG_yUnz97MY": {"name": "Receive Only"}, "maK7ewEZGZ8cZBrUi": {"name": "Send Only"}, "mNQnTBTzCoGbWKQvH": {"name": "Vague"}, "mdcDPiaYhXEp16KqY": {"name": "Directional Sound"}, "mIZh1pg6Ib3CKRrO1": {"name": "Gravity Ripple"}, "mmdrwky4UiQAY9zVM": {"name": "Neutrino"}, "mB87hNAhzKwFhb6bf": {"name": "Sonar"}, "mxFz73JvtMBk3DOwg": {"name": "Burst"}, "mG-RqoYVXDMroGXef": {"name": "FTL"}, "mHNv9ZPXArNNXPA9g": {"name": "Secure"}, "mwyyoRbNQZpPG2oVz": {"name": "Sensie"}}}, "tWQUw50NWPyLcNrxf": {"name": "Vacuum Support", "tags": ["Advantage", "Exotic", "Physical"]}, "texFo8v3Wt-CYc_v1": {"name": "Vibration Sense", "tags": ["Advantage", "Exotic", "Physical"], "modifiers": {"mbqCQHButz3Kzb_2j": {"name": "Universal"}, "mbWObH21SEISxO4a0": {"name": "Sense of Perception"}, "mKBJewUPeA18Cf_BW": {"name": "Targeting"}}}}}, "Th-NUbEaYXhc8WOX4": {"name": "Attribute Modifiers", "children": {"tmF9FAYm8LmE3PPMU": {"name": "Increased Health", "tags": ["Advantage", "Attribute", "Physical"], "features": [{}]}}}, "TJlXF6gOUF33lEyDg": {"name": "Disadvantages", "children": {"t9Lq72LBRnNzrFbEj": {"name": "Electrical", "tags": ["Disadvantage", "Exotic", "Physical"]}, "tmHOVShoYrVNuFkld": {"name": "Restricted Diet (Power Cells)", "tags": ["Disadvantage", "Physical"], "modifiers": {"mW-Log16LVsu72s0F": {"name": "Substitution"}}}}}, "TKE7mmhQSK2UPVsi4": {"name": "Optional Lenses", "children": {"TwJ3W5dflhOQlp9m2": {"name": "Lens: Budding (TL12)", "tags": ["Lens"], "children": {"tZuRMDF2a7HLiLvBE": {"name": "Duplication", "tags": ["Advantage", "Exotic", "Mental", "Physical"], "modifiers": {"mNIMzhOMdsPad5BqF": {"name": "Duplicated Gear"}, "m1Mje3yg3TYsubLrt": {"name": "No Sympathetic Injury"}, "mB0WrFc_DiN1x0g4n": {"name": "Digital"}, "m6pm3h3Mzylm8rjip": {"name": "Shared Resources"}, "mPSdjTE7jiToAz_DB": {"name": "Construct"}, "mXPgseei5q7-gBaJf": {"name": "Sequential"}, "mqiv2W7uaiCSf8Atn": {"name": "Multiplication"}, "mQ5U6kEZblTDSb_VO": {"name": "Duplicate is -1 SM"}}}}}, "T02tpy3Hkb8OX_VLV": {"name": "Lens: Contragrav  (TL11^)", "tags": ["Lens"], "children": {"tx6SCRHI9DfQ0ZKvp": {"name": "Flight", "tags": ["Advantage", "Exotic", "Physical"], "modifiers": {"mWUALqU6V2sSvjSCQ": {"name": "Newtonian Space Flight"}, "m8gBnT7JLtuQZ8bVb": {"name": "Space Flight"}, "mPMzjJTsyFFZGSuGA": {"name": "Cannot Hover"}, "mlTDjKP2VhBSAtO12": {"name": "Controlled Gliding"}, "mVuhEOB_k2K-tgEF4": {"name": "Gliding"}, "mj94whrQF8FUAN-xX": {"name": "Lighter Than Air"}, "mY2lEYvGUuZt3Xj7C": {"name": "Low Ceiling"}, "mD2oLV1NasaFcXrB0": {"name": "Low Ceiling"}, "mYQclJPA7b9YMA527": {"name": "Low Ceiling"}, "mknWjjqHrCSpzQul6": {"name": "Small Wings"}, "mt2W2_9bFEgef9pLH": {"name": "Space Flight Only"}, "mIcLakz1ZbyxuNkKo": {"name": "Winged"}, "mW9-l1qum70WheYVx": {"name": "Planetary"}, "mRepv_4gx6ffq-Qew": {"name": "Requires Surface"}}}}}}}, "TXPrHsLYKy_OfTF9Y": {"name": "Perks", "children": {"t2DDoPCXHcTQTaUAD": {"name": "Accessory (Compact microframe computer)", "tags": ["Exotic", "Perk", "Physical"]}}}, "TKpnWQWzetkfviEmO": {"name": "Secondary Characteristic Modifiers", "children": {"tvygreVL1vmxYWY_Q": {"name": "Extra Hit Points", "tags": ["Advantage", "Attribute", "Physical"], "modifiers": {"m9Rgt4GsdmkRiLUM6": {"name": "Size"}, "mH6HnqWMCe28SAZCw": {"name": "No Fine Manipulators"}}, "features": [{}]}, "tH1ycZTrNHf30WgxP": {"name": "Increased Perception", "tags": ["Advantage", "Attribute", "Mental", "Physical"], "features": [{}]}}}, "TXBnwLbE5RqkpizY8": {"name": "TL Lenses", "children": {"TdFhbZDBzqZ4RLpGr": {"name": "Lens: TL11 Model", "tags": ["Lens"], "children": {"tEii5GsZiNDW-Skl-": {"name": "Maintenance", "tags": ["Disadvantage", "Physical"], "modifiers": {"mhyphpjqYO-dHRUeF": {"name": "People Required: 1"}, "mK2n-W5VxpEULSpwN": {"name": "People Required: 2"}, "maxZojIjqWvnolmoF": {"name": "People Required: 3-5"}, "mEHKplrsJuFwqcl1X": {"name": "People Required: 6-10"}, "mvkIvgh1jZN8UXXYa": {"name": "People Required: 11-20"}, "mPS8lmmsFc8bAK-G7": {"name": "People Required: 21-50"}, "mF6kf0f9Iq1cIk8zH": {"name": "People Required: 51-100"}, "m3ckZ7rnk7KE5cDF0": {"name": "People Required: 101-200"}, "msbZ6taZfO4alCpil": {"name": "People Required: 201-400"}, "mo5XaBwOkz92-4H0u": {"name": "People Required: 401-800"}, "mgrWPEJrHTRI-wxTa": {"name": "People Required: 801-1600"}, "mqle_ftu3YsE8hbpH": {"name": "People Required: 1601-3200"}, "mpFhQiuZaq5ht2r66": {"name": "People Required: 3201-6400"}, "m0sf3Ds9qlKVLoqze": {"name": "People Required: 6401-12800"}, "mWp6OqDpM6ICiGqwZ": {"name": "People Required: 12801-25600"}, "mBu2_RjmMccrKgkTG": {"name": "Frequency: Monthly"}, "myQfv9SjL3syPYL7E": {"name": "Frequency: Bi-weekly"}, "m3RHNR7x05Y_ngh20": {"name": "Frequency: Weekly"}, "m-JBP9BLlHjy8dxpi": {"name": "Frequency: Every other day"}, "mQe2DaLGuubhfC5vG": {"name": "Frequency: Daily"}, "mRh-HKunGEe0Warul": {"name": "Frequency: Twice daily"}, "mMFc8NF8GK7OjslbQ": {"name": "Frequency: Three to five times daily"}, "mqihEX4kw3k3QSAD_": {"name": "Frequency: Constant"}}}, "tCW08YrnGz7F2vpSV": {"name": "Reduced Consumption", "tags": ["Advantage", "Physical"], "modifiers": {"mkit2lNhjqIrT2A1l": {"name": "Cast-Iron Stomach"}, "mgVtuac6BAtSBFDem": {"name": "Food Only"}, "mb0Myy-uROiNckqVg": {"name": "Water Only"}}}}}, "T947afCnc6dHeAaVc": {"name": "Lens: TL12 Model", "tags": ["Lens"], "children": {"tIhXrwxHb6eLBrAgW": {"name": "Reduced Consumption", "tags": ["Advantage", "Physical"], "modifiers": {"mNQBZbuc9O9eOFGw0": {"name": "Cast-Iron Stomach"}, "mgjxaCqsEJxPNu02e": {"name": "Food Only"}, "m9oh8w1yyIO3twUCz": {"name": "Water Only"}}}}}}}}}}}